Workbook
Name __Res1: #REF!
Name _MailOriginal: Notifications!$I$11
Name _Res1: #REF!
Name _sam2: '[1]Validate '!#REF!
Name BF_Analytics: #REF!
Name comm1: #REF!
Name comm2: #REF!
Name comm3: #REF!
Name comm4: #REF!
Name core: #REF!
Name core1: '[2]Voyager Services Proposal'!$A$466
Name corp: '[3]Project Scope'!#REF!
Name corpend: '[3]Project Scope'!#REF!
Name dnrTaskList: OFFSET('[4]Sys Config'!$G$13,,,COUNTA('[4]Sys Config'!$G$13:$G$65536),1)
Name duration: #REF!
Name duration2: #REF!
Name endnew: '[5]Project Scope'!#REF!
Name enduser: #REF!
Name functionality: #REF!
Name IA_Analytics: #REF!
Name interface: #N/A
Name interfaces: #REF!
Name new: '[5]Project Scope'!#REF!
Name no: '[5]Project Scope'!#REF!
Name nonew: '[5]Project Scope'!#REF!
Name not: '[3]Project Scope'!#REF!
Name notcorp: '[3]Project Scope'!#REF!
Name pilot: #REF!
Name ProjectDuration: #REF!
Name reports: #REF!
Name Review_Commercial_Analytics___Property___Rent_Roll: #REF!
Name rpt: #REF!
Name sam: '[3]Project Scope'!#REF!
Name Split: #REF!
Name Test: #REF!
Name totrpts: #REF!
Name users: [6]Assumptions!$C$19
Name validate2: '[1]Validate '!#REF!

Sheet KPI
F1: Received Status | G1: (Multiple Items)
F3: Count of Sr.No. | G3: Column Labels
F4: Departments | G4: Grand Total
F5: Grand Total
F16: Count of Sr.No. | G16: Column Labels
F17: Departments | G17: (blank) | H17: Grand Total
F18: Finance | G18: 14 | H18: 14
F19: Procurement | G19: 19 | H19: 19
F20: Grand Total | G20: 33 | H20: 33
J24: =32/82 -> 0.3902439

Sheet RFI Index
A1: XX
A2: Request for Information
A3: Sr.No. | B3: Yardi Module | C3: BPR Reference | D3: Requirements (What we want?) | E3: Department | F3: Priority | G3: Project Team Member | H3: Shared Date | I3: Target Date | J3: Received Status | K3: Received Date | L3: Remarks | M3: Closure remarks | N3: Delayed Days | O3: Dependency | P3: Configured in Live
A4: 1 | B4: Vendor Café | C4: P2P3 | D4: Vendor Markets | E4: Procurement | F4: High
A5: =A4+1 -> 2 | B5: Vendor Café | C5: P2P4, P2P5 | D5: Vendor Categories and Insurance Types | E5: Procurement | F5: High
A6: =A5+1 -> 3 | B6: Vendor Café | C6: P2P6,P2P8 | D6: Vendor Workflow | E6: Procurement | F6: Critical
A7: =A6+1 -> 4 | B7: Vendor Café | C7: P2P7 | D7: Mandatory documents for Vendor Registration | E7: Procurement | F7: Low
A8: =A7+1 -> 5 | B8: Vendor Café | C8: P2P14 | D8: Vendor User Defined Field | E8: Procurement | F8: High
A9: =A8+1 -> 6 | B9: Vendor Café | C9: P2P15 | D9: Vendor Agreement | E9: Procurement | F9: Low
A10: =A9+1 -> 7 | B10: Vendor Café | C10: P2P16 | D10: Vendor Cafe configurations | E10: Procurement | F10: Low
A11: =A10+1 -> 8 | B11: Vendor Café | C11: P2P17 | D11: VC Email Templates | E11: Procurement | F11: Low
A12: =A11+1 -> 9 | B12: Vendor Café | C12: P2P19 | D12: Support numbers/email | E12: Procurement | F12: High
A13: =A12+1 -> 10 | B13: Vendor Café | D13: EFT Format | E13: Finance | F13: Low
A14: =A13+1 -> 11 | B14: P2P | C14: AP1.1 | D14: Person creating PO | E14: Procurement | F14: High
A15: =A14+1 -> 12 | B15: P2P | C15: AP1.1 | D15: Person creating Invoice | E15: Finance | F15: High
A16: =A15+1 -> 13 | B16: P2P | C16: AP1.3 | D16: Provide a list of Expense types | E16: Procurement | F16: Critical
A17: =A16+1 -> 14 | B17: P2P | C17: AP1.4 | D17: PR and PO Approval Workflow | E17: Procurement | F17: Critical
A18: =A17+1 -> 15 | B18: P2P | C18: AP1.5 | D18: PO attachment types | E18: Procurement | F18: High
A19: =A18+1 -> 16 | B19: P2P | C19: AP1.6 | D19: Invoice approval DOA | E19: Finance | F19: Critical
A20: =A19+1 -> 17 | B20: P2P | C20: AP1.7 | D20: Invoice Attachment types | E20: Finance | F20: High
A21: =A20+1 -> 18 | B21: P2P | C21: AP1.10 | D21: Direct Payable attachment types | E21: Finance | F21: High
A22: =A21+1 -> 19 | B22: P2P | C22: AP1.11 | D22: Fields for EFT to be captured on bank record | E22: Finance | F22: High
A23: =A22+1 -> 20 | B23: P2P | C23: AP1.11 | D23: Invoice Payment Methods | E23: Finance | F23: High
A24: =A23+1 -> 21 | B24: P2P | C24: AP1.12 | D24: Payments approval DOA (GL Disbursment) | E24: Finance | F24: Critical
A25: =A24+1 -> 22 | B25: P2P | C25: AP1.13 | D25: Payment Attachment types | E25: Finance | F25: High
... A27: =A26+1 -> 24 | B27: P2P | C27: Additional Notes | D27: Terms and Conditions to printed on PO - Static Field | E27: Procurement | F27: High
A28: =A27+1 -> 25 | B28: P2P | D28: PO User Defined Fields | E28: Procurement | F28: High
A29: =A28+1 -> 26 | B29: P2P Services | C29: AP4.2 | D29: Service Contract DoA | E29: Procurement | F29: Critical
A30: =A29+1 -> 27 | B30: P2P Services | D30: Service Contract Business | E30: Procurement | F30: High
A31: =A30+1 -> 28 | B31: P2P Services | C31: AP4.3 | D31: Service Contract Attachments | E31: Procurement | F31: High
A32: =A31+1 -> 29 | B32: Fixed Assets | C32: FA2 | D32: Asset Group | E32: Finance | F32: High
A33: =A32+1 -> 30 | B33: Fixed Assets | C33: FA3 | D33: Asset Types | E33: Finance | F33: High
A34: =A33+1 -> 31 | B34: Fixed Assets | C34: FA4 | D34: Asset Depreciation Groups | E34: Finance | F34: High
A35: =A34+1 -> 32 | B35: Fixed Assets | C35: FA13 | D35: Fixed Asset Attachments | E35: Finance | F35: High
A36: =A35+1 -> 33 | B36: Fixed Assets | D36: Asset Process | E36: Finance | F36: High
A37: =A36+1 -> 34 | B37: Facility Manager | C37: FM1 | D37: Maintenance Models | E37: Facility Management
A38: =A37+1 -> 35 | B38: Facility Manager | C38: FM2 | D38: Team Structure | E38: Facility Management
A39: =A38+1 -> 36 | B39: Facility Manager | C39: FM3 | D39: Employee Time slots | E39: Facility Management
A40: =A39+1 -> 37 | B40: Facility Manager | C40: FM8, FM9 | D40: WO Priority | E40: Facility Management
A41: =A40+1 -> 38 | B41: Facility Manager | C41: FM10, FM11 | D41: WO Status and Change Reason | E41: Facility Management
A42: =A41+1 -> 39 | B42: Facility Manager | C42: FM7 | D42: WO Category and Subcategories | E42: Facility Management
A43: =A42+1 -> 40 | B43: Facility Manager | C43: FM12 | D43: WO Attachments | E43: Facility Management
A44: =A43+1 -> 41 | B44: Facility Manager | D44: WO SLA KPI and Due Date Default | E44: Facility Management
A45: =A44+1 -> 42 | B45: Facility Manager | D45: Employee Skills | E45: Facility Management
A46: =A45+1 -> 43 | B46: Facility Manager | D46: Work Order Roles and Workflow | E46: Facility Management
A47: =A46+1 -> 44 | B47: Facility Manager | C47: FM18 | D47: WO Config Points | E47: Facility Management
A48: =A47+1 -> 45 | B48: Facility Manager | C48: IN1 | D48: Inspection Process | E48: Facility Management
A49: =A48+1 -> 46 | B49: Facility Manager | C49: IN8 | D49: Inspection Statuses | E49: Facility Management
A50: =A49+1 -> 47 | B50: Facility Manager | C50: PPM2 | D50: PM Process | E50: Facility Management
A51: =A50+1 -> 48 | B51: Facility Manager | C51: IN8 | D51: PM Statuses | E51: Facility Management
A52: =A51+1 -> 49 | B52: Facility Manager | C52: IN7 | D52: Inspections & PPM Config Points | E52: Facility Management
A53: =A52+1 -> 50 | B53: Facility Manager | D53: Auto Assignment Rules | E53: Facility Management
A54: =A56+1 -> 53 | B54: Facility Manager | D54: Equipments Systems & Types | E54: Facility Management | L54: ETL
A55: =A53+1 -> 51 | B55: Facility Manager | D55: PPM Check lists | E55: Facility Management | L55: ETL
A56: =A55+1 -> 52 | B56: Facility Manager | D56: Equipments | E56: Facility Management | L56: ETL
A57: =A54+1 -> 54 | B57: Facility Manager | C57: IN9 | D57: Inspection Templates | E57: Facility Management | L57: ETL
A58: =A55+1 -> 52 | B58: Facility Manager | D58: Warehouse Locations | E58: Facility Management | L58: ETL
A59: =A56+1 -> 53 | B59: Facility Manager | D59: Item Categories | E59: Facility Management | L59: ETL
A60: =A59+1 -> 54 | B60: Facility Manager | D60: Item Type | E60: Facility Management | L60: ETL

Sheet Sheet1
A1: Requirements (What we want?) | B1: Received Status
A2: Guest Template | B2: =VLOOKUP(A2,'RFI Index'!D:J,7,0) -> #N/A | D2: Rent - Car Parking - Guest Template / SRS?
A3: Applicant/Tenant Charge Fees Matrix | B3: =VLOOKUP(A3,'RFI Index'!D:J,7,0) -> #N/A
A4: Tenant Service requests and DOA | B4: =VLOOKUP(A4,'RFI Index'!D:J,7,0) -> #N/A
A5: Chart of Accounts (COA) | B5: =VLOOKUP(A5,'RFI Index'!D:J,7,0) -> #N/A
A6: Charge codes | B6: =VLOOKUP(A6,'RFI Index'!D:J,7,0) -> #N/A
A7: BD Workflows - Approving LL leads (Service request) | B7: =VLOOKUP(A7,'RFI Index'!D:J,7,0) -> #N/A
A8: Attachment Types under this process | B8: =VLOOKUP(A8,'RFI Index'!D:J,7,0) -> #N/A
A9: BD Workflows - APproving Head leases (Amendment WF) | B9: =VLOOKUP(A9,'RFI Index'!D:J,7,0) -> #N/A
A10: Charge codes for head lease | B10: =VLOOKUP(A10,'RFI Index'!D:J,7,0) -> #N/A
A11: Lease Type for head lease | B11: =VLOOKUP(A11,'RFI Index'!D:J,7,0) -> #N/A
A12: Type of activites to be tracked at headlease proposal | B12: =VLOOKUP(A12,'RFI Index'!D:J,7,0) -> #N/A
A13: Requirements for lessee accounting - GL accounts, etc. | B13: =VLOOKUP(A13,'RFI Index'!D:J,7,0) -> #N/A
A14: Holdover process for Head Lease | B14: =VLOOKUP(A14,'RFI Index'!D:J,7,0) -> #N/A
... A33: Legal Notifications | B33: =VLOOKUP(A33,'RFI Index'!D:J,7,0) -> #N/A

Sheet Notifications
A1: Return
A2: To be taken from AIM (Still under development)
A4: BPR Ref # | B4: Yardi Template Reference | C4: Entity | D4: Property | E4: Process Name | F4: Notification Description | G4: Recipients | H4: When to send notifications? Trigger | I4: Email Format | J4: SMS Format

Sheet Takeover-Scenarios
A1: Return
C2: Managed Properties | D2: Investment Properties
A3: 1 | B3: Pending Renewals of Tenants as of Take-over Date
A4: 2 | B4: Commercial Tenants - All scenarios for commercial tenants with VAT & along with treatment for Investment properties and managed properties. This should be based on all types for invoicing frequency – Annual, Half yearly, Quarterly etc.
A8: LL Handover Scenario
A9: Project Profitablity Report : - Customization
A10: Income/Expenses report apportioned based on Head Lease LL contract Period esp in days.
A11: This is required for Property profitability analysis as the LL Management contract renewal is based on the same.
A12: This is required only for the reporting purpose for decision making for future renewals of head leases.
A14: In case of Investment properties, the requirement is to review the complete profitability after considering the head lease expenses/AMCs/Other expenses and income from subleases (Rent, Admin other income) for decision making for renewals etc.
A15: Example :
A16: Head Lease Period - 08-July-2023 to 07-Aug-2024
A17: Sublease period - 15-Sept-2023 to 14-Sept-2024.
A18: In this case Driven would require the details to identify the full revenue/expenses recognized for the investment property till end date of the head lease contract i.e. LL Handover date only i.e. 07-Aug-2024.

Sheet Takeover-Tenant Settlement
A1: Return
A4: 1 | B4: Tenant Settlement document Samples/Format with possible scenarios.

Sheet Tenant Handover settlement-scen
A3: Scenario -1
A4: Investment properties
A5: Cut-off | B5: 45169
A6: Tenant -1 | E6: Reponsibility | G6: Remarks
A7: Rent -1 | B7: 45078 | C7: 20000 | D7: Cleared | E7: Driven
A8: Rent -2 | B8: 45139 | C8: 20000 | D8: Cheque bounced | E8: Driven | F8: Aug-Sept | G8: Overlapping Period
D9: Tenant Pays to Driven | F9: 20000 | G9: Driven will keep 10k & handover 10k to LL
D10: Tenant Pays to LL | G10: LL will handover 10k for Aug to Driven
D11: Legal Case
A12: Rent -3 | B12: 45200 | C12: 20000 | D12: Cheque bounced | E12: LL

Sheet PMA Renewals
A3: Driven - LL Agreement Renewals (Change in Agreement Type)
A5: 1 | B5: Managed Property to Investment property
B6: Tenant Security Deposit - Held in LL bank | C6: LL to handover to Driven
B7: Tenant Security Deposit - Held in Driven Bank | C7: LL to agree tranfer of SD in to Driven Name
B8: Tenant O/s in managed property as of cut-off date
B9: Tenant advances in managed property as of cut-off date
A12: 2 | B12: Investment property to Managed Property
B13: Tenant Security Deposit
B14: Tenant O/s in managed property as of cut-off date
B15: Tenant advances in managed property as of cut-off date
A17: 3 | B17: Managed Property to Managed Property
B18: PM fees % change
B19: PM Fees calculation methods | C19: New Fee pool based on newly agreed terms to be created & Mapped to Property
A21: 4 | B21: Investment property to Investment Property
B22: Change in Rent Remuneration to LL | C22: Renewal to be processed for Head lease in system.
B23: Some time negotiation is still in process after contract expiry, Driven would be recognizing the rent exps based on earlier contract. | C23: 1. Check if Rent exps calculation can be generated from system. 2. JE with reverse next month would be entered to book Rental exps.

Sheet Vendor Markets
A1: Return
A2: Sr.no. | B2: Markets
A3: 1 | B3: Local
A4: 2 | B4: International

Sheet Vendor Cat & Ins
B1: Return
B3: Vendor Categories and Insurance
B4: Category Name | C4: Insurance Setup | D4: Consultant Comments
B6: Supplier Goods & Services | D6: Added to Master DB
B7: Contractor | C7: Third-Party Liability, Workers' Compensation/ Employers' Liability, Contractors' All Risk (CAR) Insurance | D7: Added to Master DB
B8: Authority | D8: Added to Master DB
B9: Internal / One time vendor | D9: Added to Master DB
B15: Insurance Setup
B16: Insurance type | C16: Consultant Comments
B17: Third-Party Liability
B18: Workers' Compensation/ Employers' Liability
B19: Contractors' All Risk (CAR) Insurance
B25: ADCG
B26: Imkan | C26: Real Estate Development Business
B27: Imkan Estates | C27: Shared services for anything related to Imkan
B28: Asseto | C28: Property Management | D28: Manages both commercial and residential
B30: Accounting

Sheet Bank Structure
D5: Asseto estate | F5: Imkan P1 (only commercial) | G5: ADCG P1 (Residential and Commercial)
C6: Budget | D6: Opex
E7: Vehicles | F7: Service charges | G7: Community charges
E8: FF&F | F8: Marketing Expenses | G8: Marketing Expenses
E9: IT | F9: Legal fees | G9: Legal fees
E10: Payroll | F10: Leasing Consultancy and RDD
E11: Shared Services (Legal, Marketing etc.)
D12: Capex
E22: Entity | F22: GL Account | G22: Dr | H22: Cr
E23: Baniyas Tower | F23: AMC Cost | G23: 2000
F24: AP | H24: 2000

Sheet WF for Vendors
A1: Return
A2: Vendor Workflow (DOA)
A4: Category: | B4: All Categories
A6: Sr No. | B6: Object | C6: Process Name | D6: Step No. | E6: Workflow Step | F6: Responsible Role | G6: Next Step | H6: Modification Step | I6: Completion Step | J6: Rejection Step | K6: KPI-Completion Days
A7: 1 | B7: Vendor | C7: Vendor Approval | D7: 1 | E7: New Vendor | F7: Procurement officer | G7: Finance Review
F8: AP Accountant
D10: 2 | E10: Finance Review | F10: Finance Manager | G10: Approved
F11: AP Accountant | G11: Rejected
G12: Modifications Required
D14: 3 | E14: Approved | I14: Yes
D15: 4 | E15: Rejected | J15: Yes
D16: 5 | E16: Modifications Required | H16: Yes
E18: Originator not to be final approval
A21: Consultant Comments | B21: Added to Master DB

Sheet Vendor Attachment types
A1: Return
A6: Sr No | B6: Object Name | C6: Attachment Type | D6: Mandatory | E6: Consultant Comments
A8: 1 | B8: Vendor | C8: Trade License | D8: Yes | E8: Added to Master DB
A9: 2 | B9: Vendor | C9: Tax Certificate | D9: Yes | E9: Added to Master DB
A10: 3 | B10: Vendor | C10: Complete Company Profile/Brochure | E10: Added to Master DB
A11: 4 | B11: Vendor | C11: Bank Details Letter | D11: Yes | E11: Added to Master DB
A12: 5 | B12: Vendor | C12: Emirates ID | E12: Added to Master DB
A13: 6 | B13: Vendor | C13: POA | E13: Added to Master DB
A14: 7 | B14: Vendor | C14: Management Sys. Certificate | E14: Added to Master DB
A15: 8 | B15: Vendor | C15: Financial Statement | E15: Added to Master DB
A16: 9 | B16: Vendor | C16: Supplier Code of Conduct | E16: Added to Master DB
A17: 10 | B17: Vendor | C17: Vendor Registration Form | E17: Added to Master DB
A18: 11 | B18: Vendor | C18: Non Disclosure Agreement | E18: Added to Master DB
A19: 12 | B19: Vendor | C19: COI | D19: Yes | E19: Added to Master DB

Sheet Vendor UDFs
A1: Return
A3: # | B3: Vendor User Defined fields | C3: Field Format (Date/Text/List values/Number) | D3: Mandatory | E3: Consultant Comments
A4: 1 | B4: Vendor Category | C4: Goods, Services, Consultant, AMC, Contractor | D4: ✅ Mandatory | E4: Added to Master DB
A5: 2 | B5: Trade License name | C5: Text | D5: ✅ Mandatory
A6: 3 | B6: Trade License # | C6: Text | D6: ✅ Mandatory
A7: 4 | B7: Trade License Expiry | C7: Date | D7: ✅ Mandatory
A8: 5 | B8: VAT Certificate Expiry | C8: Date | D8: ✅ Mandatory
A9: 6 | B9: Authorized Signatory Name | C9: Text | D9: ✅ Mandatory
A10: 7 | B10: Type of Entity/Tax Classification | C10: List (Free Zone^Government^Main Land) | D10: Optional

Sheet Vendor Agreement
A1: Return
A2: Vendor Agreement
A3: Below is the standard agremeent in Yardi:
A4: Vendor agreement can be configured based on Legal requirements. (Max length: 5000 characters)
B6: You ("Vendor") have requested that Nasser Abdulla Hussain Lootah and/or its subsidiaries or affiliates (collectively "Client") consider purchase of Vendor's products or services. Vendor agrees that, as a condition of this Agreement, it will keep registration current at all times. Vendor further understands and agrees that it will provide proof of insurance as required by Client, including naming Client as an additional insured on Vendor's general liability policy. The proof of insurance required will be based on Vendor's stated industry code and identified location of operation. Vendor agrees to indemnify and hold harmless Client(i) from any damage, claim, or loss arising out of Vendor's inaccurate statement or choice of industry code and/or identified location of operation and (ii) if any employee of Vendor, or independent contractor hired by Vendor, suffers a work-related injury or illness and makes a claim against Client. This Agreement does not reduce any obligation Vendor has or may have under any other written agreement with Client nor does it constitute an obligation by Client to actually engage Vendor or purchase its products or services.

Sheet VC configurations
A1: Return
B2: Key Configurations are highlighted in yellow.
B3: Non highlighted rows are recommended standard configurations
B5: Description | C5: Value
B6: Dashboard
B7: Approved Invoices Tab Required | C7: Yes
B8: Default Time Interval in Search Filters | C8: 365
B9: Maximum Time Interval Allowed for Search Filters | C9: 365
B10: Messages Count Required | C10: Yes
B11: Not Submitted Invoices Tab Required | C11: Yes
B12: Paid Invoices Tab Required | C12: Yes
B13: Pending Invoices Tab Required | C13: Yes
B14: Purchase Orders Tab Required | C14: Yes
B15: Rejected Invoices Count Required | C15: Yes
B16: Service Contract Tab Required | C16: Yes
B17: Vendor Ledger Tab Required | C17: Yes
B18: Invoice Processing
B19: Allow Deletion of Line Items on Invoice Screen | C19: No
B20: Allow Duplicate Invoice No. | C20: No
B21: Allow Invoice Amount Greater Than PO Amount | C21: No
B22: Allow Invoice Line Item Amount Greater than PO Line Item Amount | C22: No
B23: Allow Invoicing Against Received POs Only | C23: Yes
B24: Allow PDF Image Upload on Data Invoice | C24: Mandatory
B25: Inactive Property Alert Message | C25: This property no longer accepts invoice uploads after [insert property handover date + 60days] due to a sale or change in property management. Please contact the new property management company directly for guidance on submitting invoices.
B26: Invoice Description Mandatory | C26: Yes
B27: PO Mandatory | C27: No
B28: Post Invoice to Voyager as | C28: Invoice
B29: Show Credit option in Invoice Type selection | C29: Yes
B30: Show Invoice Due Date | C30: Yes
... B32: Show Upload PDF Invoice Tab | C32: Yes
B33: Profile
B34: Allow Multiple International EFT Setup | C34: Yes
B35: Document Mandatory On Insurance Information Tab | C35: No
B36: Documents Required | C36: Mandatory
B37: Editable Market | C37: No
B38: Get Contact Types From Voyager | C38: No
B39: Markets Required | C39: Yes
B40: Maximum Vendor Document Upload Size In MB | C40: 30
B41: Show EFT Tab in Vendor Profile | C41: Yes
B42: Show Insurance Tab in Vendor Profile | C42: Yes
B43: Show Vendor Agreement Tab | C43: Yes
B44: Vendor Auto Approval Setup - Profile Amendments
B45: Auto Approve Change In Business Name | C45: No
B46: Auto Approve Change In EFT | C46: No
B47: Auto Approve Change In Legal Name | C47: No
B48: Auto Approve Changes In Address | C48: No
B49: Auto Approve Changes in Insurance | C49: No
B50: Auto Approve If Vendor Corporate Contact Email Changed | C50: No
B51: Auto Approve if New Contact Added | C51: Yes
B52: Auto Approve if documents uploaded | C52: No
B53: Vendor Shield
B54: Allow Invoicing for Non-Compliant Payment for Days | C54: 0
B55: Allow Invoicing for Non-Compliant Vendors for Days | C55: -
B56: Allow Invoicing for Registration Pending Vendors for Days | C56: 0
B57: Auto Reject Vendors If All Properties Are Non-compliant | C57: No
B58: Auto Reject Vendors If Universal Check Components Are Non-compliant | C58: No
B59: Compliant Properties Threshold | C59: 75
B60: Default Vendor Shield Payment By | C60: Vendor
B61: Inactivate Non-Compliant Vendors in Voyager | C61: No
B62: Message For Non-Compliant But Approved Vendor | C62: Even though you are Non-Compliant based on the above Compliance checks, the client has marked you compliant and approved. You can continue using Vendor Cafe services.
B63: Require Compliance Data Before Invoicing | C63: No
B64: Require Workers Comp Exemption Form | C64: No
B65: Show Insurance Override option in Accept/Approve screen. | C65: No
... B70: Vendor Cafe - Vendor Property Security | C70: No
B71: Other
B72: Activation Expiry Days (Vendor Invite Link) | C72: 15
B73: Allow Vendor Sync without Tax ID | C73: No
B74: Allow to Invite Vendor With Same Email or Tax ID | C74: Yes
B75: Attach Quick Start Guide to Vendor Invite Mail | C75: Yes
B76: Auto Sync Vendors (based on UDF Criteria) | C76: Yes
B77: Auto-Generate Vendor Code | C77: Yes
B78: Category Optional on New Invites | C78: No
B79: Create User for Contacts Synced from Voyager | C79: No
B80: Delete More Than 30 Days Unsent Invites | C80: No
B81: Do Not Send Registration Reminders After | C81: 15
B82: Do not show unread Q&A count after | C82: 30
B83: Email Id for Vendor Cafe Support
B84: Payment Method For New Vendors | C84: EFT
B85: Phone Number for Vendor Cafe Support
B86: Trigger Workflow in Voyager on Vendor approval | C86: For New Vendor Invites
B87: Update Consolidate Flag in Voyager | C87: Yes
B88: Update Insurance Dates in Voyager | C88: Yes
B89: Update UDFs in Voyager | C89: Yes
B90: Voyager - Auto Sync Properties | C90: Yes
B91: Voyager - Vendor Property Security | C91: Yes
B92: Voyager- Sync Property Mapping | C92: Yes
B93: While New Invite Check Voyager For Duplicate Vendor | C93: Yes

Sheet VC Email Templates
A1: Return
B4: Sr.No | C4: Email Template Name | D4: Email Trigger Description | E4: Template
B5: 1 | C5: EFT data submitted notification template 1 | D5: EFT_DATA_SUBMITTED_NOTIFICATION | E5: Your Electronic File Transfer (EFT) has been successfully submitted through the Vendor Portal. The submission will now be reviewed by the Avison Young Procurement Team. You will receive a further notification once the review is complete. Submission Details: Vendor Name: [Vendor_Name] Submission ID: [EFT_Reference_ID] Submission Date: [Date_Timestamp] No further action is required at this time. For questions or support, please contact Procurement Support Email
B6: 2 | C6: EFT rejected template 1 | D6: EFT_REJECTED_NOTIFICATION | E6: Your Electronic File Transfer (EFT) submission has been reviewed and rejected by the Avison Young Procurement Team. Reason for Rejection: [Insert specific reason, e.g., "Missing mandatory supporting documentation" or "Incorrect PO reference number"] Please review the details, make the necessary corrections, and resubmit your EFT file through the Vendor Portal. If you require further guidance, please contact the Procurement Team at Procurement Support Email
B7: 3 | C7: Registration Done Notification Template 1 | D7: REGISTRATION_DONE_NOTIFICATION | E7: Thank you for completing your registration on the Avison Young Vendor Portal. Your account has been successfully created and is now under review by the Procurement Team. You will be notified once your registration has been approved and access is fully enabled. Registration Details: Vendor Name: [Vendor_Name] Registration ID: [Registration_ID] Submission Date: [Date_Timestamp] If you have any questions or need assistance, please contact us at Procurement Support Email
B8: 4 | C8: Registration Invite Template 1 | D8: VENDOR_REGISTRATION_INVITE | E8: You have been invited to register as a vendor with Avison Young via our Vendor Portal. To begin the registration process, please follow the link below and complete the required information: [Registration_Link] Instructions: Complete your company profile and banking information Upload any required compliance documents Submit your registration for review Once submitted, your application will be reviewed by the Avison Young Procurement Team. You will be notified upon approval. If you have any questions or require assistance, please contact us at Procurement Support Email
B9: 5 | C9: User Activation Notification Template 1 | D9: USER_ACTIVATION_NOTIFICATION | E9: Your user account for the Avison Young Vendor Portal has been successfully activated. You may now log in and begin using the system to manage your vendor profile, submit invoices and credit notes, and track purchase orders and other procurement activities. Account Details: User Name: [User_Name] Email: [User_Email] Activation Date: [Activation_Timestamp] Portal Access: [Vendor_Portal_URL] If you have any questions or require support, please contact the Procurement Team at Procurement Support Email We’re glad to have you on board.

Sheet VC Support emails
A1: Return
A3: Support Information to be displayed to vendor in Vendor Café
A5: Type | B5: Information
A6: Phone number
A7: Email

Sheet Vendor EFT format
A2: Return
B5: Fields | C5: Mandatory(Yes/No)
B6: Beneficiary Name | C6: Yes
B7: Bank Name | C7: Yes
B8: IBAN | C8: Yes
B9: Account Number | C9: Yes
B10: Branch Name | C10: Yes
B11: Swift code | C11: Yes
B15: Consultant Comments | C15: Configured on Master DB

Sheet Person creation PO
A1: Return
A3: Person creating Purchase Order in the system:
A4: Still no separate team for procurement team
A7: Sr No | B7: Legal Entity | C7: Property | D7: Role | E7: Task
A8: 1 | B8: All | C8: All Properties | D8: FM Manager | E8: PR Creation
D9: Document Control
D10: PM Admin
A11: 2 | B11: All | C11: All Properties | D11: FM Manager | E11: PO Creation
D12: FM Manager
D13: Document Control
D14: PM Admin
A15: 3 | B15: All | C15: All Properties | D15: FM Technician | E15: GRN
A18: 4 | B18: All | C18: All Properties | E18: Create PR via PO

Sheet Person Creating Invoice
A1: Return
A4: Sr No | B4: Legal Entity | C4: Property | D4: Role | E4: Purpose
A5: 1 | B5: All | C5: All | D5: AP accountant | E5: Elevate - All invoices
A6: 2 | B6: All | C6: All | D6: Vendor | E6: Vendor Café
A7: 3 | B7: All | C7: All | D7: FM Manager | E7: Person doing GRN

Sheet Expense Type
B1: Return
B3: Expense types | C3: Consultant Comments
B4: Legal
B5: Security
B6: Facility Management
B7: Insurance
B8: Utilities
B9: Service Charge
B10: Admin
B11: IT
B12: Marketing
B13: HR
B14: Property Management
B15: Authoritiy Fees
B16: Service Contract

Sheet PO Approval DOA
A1: Return | F1: Consultant Comments | G1: Added to Master DB
A3: Expense type: All
A5: Sr No. | B5: Object | C5: Process Name | D5: Step No. | E5: Workflow Step | F5: Responsible Role | G5: Next Step | H5: Amount From | I5: Amount To | J5: Modification Step | K5: Rejection Step | L5: Completion Step
A6: 1 | B6: Purchase Order | C6: Core_PR/PO | D6: 1 | E6: New PR | F6: PM Admin | G6: PR - PM Manager Approval | H6: 0 | I6: 2999.99
F7: PM Admin | G7: PR - Landlord Approval | H7: 3000 | I7: 999999
F8: Requester
D9: 2 | E9: PR - Landlord Approval | F9: Asset Manager | G9: PR - PM Manager Approval
G10: Reject
G11: Modification Required
D12: 3 | E12: PR - PM Manager Approval | F12: PM Manager | G12: PO - GM Approval
G13: PO - Finance Review
G14: PO - Finance Review
G15: Reject
G16: Modification Required
D18: 4 | E18: PO - GM Approval | F18: General Manager | G18: PO - Finance Review
G19: Rejected
G20: PO - Modification Required
D22: 5 | E22: PO - Finance Review | F22: Finance Manager | G22: Approved
G23: Rejected
G24: PO - Modification Required
D26: 6 | E26: PO - XX Approval | F26: XX | G26: XX
G27: XX
G28: Rejected
G29: PO - Modification Required
D31: 6 | E31: PO - XX Approval | F31: XX | G31: XX
G32: XX
G33: Rejected
G34: PO - Modification Required
D35: 7 | E35: Approved | L35: Yes
D36: 8 | E36: Rejected | K36: Yes
D37: 9 | E37: PO - Modification Required | F37: Procurement Officer | G37: PO - Procurement Manager Approval | J37: Yes
A39: Expense type: Other Expenses
A41: Sr No. | B41: Object | C41: Process Name | D41: Step No. | E41: Workflow Step | F41: Responsible Role | G41: Next Step | H41: Amount From | I41: Amount To | J41: Modification Step | K41: Rejection Step | L41: Completion Step
A42: 1 | B42: Purchase Order | C42: Core_PR/PO | D42: 1 | E42: New PR | F42: Admin | G42: PR - Department Manager Approval
F43: Requester
D45: 2 | E45: PR - Department Manager Approval | F45: Marketing Manager | G45: PO - Finance Review
F46: IT Manager | G46: PO - Finance Review
F47: Admin Manager | G47: PO - Finance Review
G48: Reject
G49: Modification Required
D51: 3 | E51: PO - Finance Review | F51: Finance Manager | G51: PO - GM Approval
G52: Rejected
G53: PO - Modification Required
D55: 4 | E55: PO - GM Approval | F55: General Manager | G55: Approved
G56: Rejected
G57: PO - Modification Required
D59: 5 | E59: PO - XX Approval | F59: XX | G59: XX
G60: XX
G61: Rejected
G62: PO - Modification Required
D64: 6 | E64: PO - XX Approval | F64: XX | G64: XX
G65: XX
G66: Rejected
G67: PO - Modification Required
D68: 7 | E68: Approved | L68: Yes
D69: 8 | E69: Rejected | K69: Yes
D70: 9 | E70: PO - Modification Required | F70: Procurement Officer | G70: PO - Procurement Manager Approval | J70: Yes

Sheet Invoice Approval DOA
A1: Return | E1: Consultant Comments | F1: Added to Master DB
A2: Expense type: Facilities
A3: Sr No. | B3: Object | C3: Process Name | D3: Step No. | E3: Workflow Step | F3: Responsible Role | G3: Next Step | J3: Modification Step | K3: Rejection Step
A4: 1 | B4: Invoice Register | C4: Invoice approval | D4: 1 | E4: Add invoice | F4: Accountant | G4: Send for Fianance Review
D5: 2 | G5: Modify invoice
G6: Reject Invoice
D8: 3 | E8: Send for Finance Review | F8: Finance Manager | G8: Approve Invoice
G9: Modify invoice
G10: Reject Invoice
F11: Finance Manager | G11: Approve Invoice
G12: Modify invoice
G13: Reject Invoice
D14: 4 | E14: Approve Invoice | G14: Approved
D15: 5 | E15: Modify invoice | F15: Accountant | G15: Review invoice | J15: Yes
D16: 6 | E16: Reject Invoice | F16: Accountant | G16: Rejected
A18: Expense type: All
A19: Sr No. | B19: Object | C19: Process Name | D19: Step No. | E19: Workflow Step | F19: Responsible Role | G19: Next Step | H19: Amount From | I19: Amount To | J19: Modification Step | K19: Rejection Step | L19: Completion Step | M19: KPI-Completion Days
A20: 1 | B20: Invoice Register | C20: Invoice approval | D20: 1 | E20: New Invoice | F20: AP Accountant | G20: Finance Manager Review
F21: Vendor Café | G21: Finance Manager Review
F22: Originator | G22: Finance Manager Review
D23: 2 | E23: Finance Manager Review | F23: Finance Manager | G23: Approved
G24: Rejected
G25: Modification Required
D26: 3 | E26: Approved | L26: Yes
D27: 4 | E27: Rejected | K27: Yes
D28: 5 | E28: Modification Required | F28: AP Accountant | G28: Finance Manager Review | J28: Yes

Sheet Bank EFT
A1: Return | B1: 7
A2: Bank Accounts
A4: Information to be captured on bank account(client's, Vendor's, Tenant's)
A5: Add fields that are required as per business requirements
A7: Fields | B7: Mandatory(Yes/No)
A8: Beneficiary Name | B8: Yes
A9: Beneficiary Address 1 | B9: Yes
A10: IBAN | B10: Yes
A11: Beneficiary Bank Name | B11: Yes
A12: Beneficiary Bank Address 1 | B12: Yes
A13: Swift code | B13: Yes
A14: Account Number | B14: Yes

Sheet Payment Approval
A1: Return
A2: Expense Type: Gldisbu.
A3: Sr No. | B3: Object | C3: Process Name | D3: Step No. | E3: Workflow Step | F3: Responsible Role | G3: Next Step | H3: Modification Step | I3: Rejection Step | J3: Completion Step | K3: KPI-Completion (Days)
A4: 1 | C4: Service Contract | D4: 1 | E4: New Service Contract | F4: FM Manager | G4: General Manager Approval
D7: 2 | E7: General Manager Approval | F7: General Manager | G7: Finance Review
G8: Reject
G9: Modification Required
D11: 3 | E11: Finance Review | F11: Fianance Manager | G11: Approve
G12: Modification Required
D13: 4 | E13: Approved | J13: Yes
D14: 5 | E14: Rejected | I14: Yes
D15: 6 | E15: Modification Required | F15: FM Manager | G15: General Manager Approval | H15: Yes

Sheet Payment methods
A1: Return
A3: Payment methods to Vendors
A4: Sr No | B4: Method
A5: 1 | B5: Cheque
A6: 2 | B6: Cash
A7: 3 | B7: EFT
A8: 4 | B8: Bank Transfer
A9: 5 | B9: Credit Card
A10: 6 | B10: Noqodi

Sheet P2P Attachment type
A1: Return
A2: Sr No | B2: Object Name | C2: Attachment Type | D2: Consultant Comments
A3: 1 | B3: Purchase Order | C3: Delivery note | D3: Added to Master DB
A4: 2 | B4: Purchase Order | C4: Quotation | D4: Added to Master DB
A5: 3 | B5: Purchase Order | C5: Comparsion sheet (CS) | D5: Added to Master DB
A6: 4 | B6: Purchase Order | C6: Maintenance Technical Report | D6: Added to Master DB
A7: 5 | B7: Purchase Order | C7: Other | D7: Added to Master DB
A8: 6 | B8: Purchase Order | C8: Job Completion Report | D8: Added to Master DB
A9: 7 | B9: Purchase Order | C9: Security Deposit docs | D9: Added to Master DB
A10: 8 | B10: Purchase Order | C10: Move in Report | D10: Added to Master DB
A11: 9 | B11: Purchase Order | C11: Tax Invoice | D11: Added to Master DB
A12: 10 | B12: Purchase Order | C12: Photo Proof | D12: Added to Master DB
A13: 11 | B13: Service Contract | C13: Job Completion Report | D13: Added to Master DB
A14: 12 | B14: Service Contract | C14: Signed Service Contract | D14: Added to Master DB
... A24: 22 | B24: Payable | C24: Job Completion Report | D24: Added to Master DB

Sheet Cancel PO
A1: Return
A4: Please explain process for Cancelling PO (See below) | B4: Finance Comments
A7: Scenario 1: PO under Workflow Approval
A8: If PO needs to be cancelled, then the same should be Rejected using the WF Rejection step | B8: Procurement Officer can conduct this if he has the necessary approvals
A10: Scenario 2: PO Approved. No Material to be received
A11: Short Close PO using the PO Close functionality | B11: All PO cancellation /Modification / any change should be with Procurement
A13: Scenario 3: PO Approved. Partial Material to be received
A14: Perform GRN, Invoice, Payment for the Partial Quantity
A15: Short Close PO using the PO Close functionality. In this case the remaining Material will not be available for further processing | B15: Full goods or services not received therefore po partially cancelled

Sheet PO T&Cs
A1: Return
A3: Purchase Order Terms and Conditions:
A4: This is static field which will be printed on all Pos across the system

Sheet PO UDF
A1: Return
A3: PO User Defined fields | B3: Field Format (Date/Text/List values/Number) | C3: Print in PO Template
A4: Requester | B4: Text | C4: No
A5: Buyer | B5: Text | C5: Yes
A6: Attention To | B6: Text | C6: Yes
A7: Payment Terms | B7: List (Advance^7 Days^30 Days^45 Days^60 Days^100% After Completion^Other) | C7: Yes
A8: Quotation Ref# | B8: Text | C8: Yes
A9: Quotation Date | B9: Text | C9: No
A22: Maximum 14 fields

Sheet Service contract DOA
A1: Return
A2: Expense Type: Service Contract
A3: Sr No. | B3: Object | C3: Process Name | D3: Step No. | E3: Workflow Step | F3: Responsible Role | G3: Next Step | H3: Modification Step | I3: Rejection Step | J3: Completion Step | K3: KPI-Completion (Days)
A4: 1 | B4: Service Contract | C4: Service Contract | D4: 1 | E4: New Service Contract | F4: FM Manager | G4: General Manager Approval
D7: 2 | E7: General Manager Approval | F7: General Manager | G7: Finance Review
G8: Reject
G9: Modification Required
D11: 3 | E11: Finance Review | F11: Fianance Manager | G11: Approve
G12: Modification Required
D13: 4 | E13: Approved | J13: Yes
D14: 5 | E14: Rejected | I14: Yes
D15: 6 | E15: Modification Required | F15: FM Manager | G15: General Manager Approval | H15: Yes

Sheet Service Contract Trade
A1: Return
B3: Service Category
B4: TFM
B5: Security
B6: Speaclized & Others
A8: For AMCs, PO accrual will be run for all eligible POs irrespective of GRN
A10: PO Deductions
A11: Date | B11: Description | C11: Deduction Reason | D11: Amount

Sheet Prepay Mapping
A1: Return
A3: Prepay mapping to be done against one prepaid expense GL account
A5: From GL Account Code | B5: To GL Account Code | C5: Mapping Account
A6: This is Expense GL Account | B6: This is Expense GL Account | C6: Asset Account for prepaid expenses deferment. | D6: Prepaid Exps GL description

Sheet Asset group
A1: Return
B2: Groups of Assets in case sub Asset types grouping is required , Asset group is used only for analytics and reporting
A5: Asset group Code | B5: Asset Group name | C5: Description | D5: Finance | E5: FM
A6: HVACMec | B6: HVACMec | C6: HVACMec
A7: Electrical | B7: Electrical | C7: Electrical
A8: Plumbing | B8: Plumbing | C8: Plumbing
A9: Barriers | B9: Barriers | C9: Barriers
A10: Fire Fighting pumps | B10: Fire Fighting pumps | C10: Fire pumps
A11: Generators | B11: Generators | C11: Generators
A12: Elevators | B12: Elevators | C12: Elevators
A13: Fire Extuinguishers | B13: Fire Extuinguishers | C13: Fire Extuinguishers
A14: CCTV | B14: CCTV | C14: CCTV
A15: Computers | B15: Computers | C15: Computers
A16: Servers | B16: Servers | C16: Servers
A17: Cell phones | B17: Cell phones | C17: Cell phones
... A23: Parking System | B23: Parking System | C23: Parking System

Sheet Asset Dep Groups
A1: Return | C1: Dep. Groups control the Dep. Method , as per BPR please consider the assets to be fully dep on the first month as a separate dep. Group
A5: Depreciation Group Code | B5: Depreciation Group Name | C5: Recovery Details (years) | D5: Debit GL | E5: Credit GL | F5: GL Book | G5: Status
A6: HVACMec | B6: HVAC/Mechanical | C6: 5 | D6: 8210-0600 | E6: 1225-0500 | F6: Accrual | G6: Depreciable
A7: Electrical | B7: Electrical | C7: 5 | D7: 8210-0600 | E7: 1225-0500 | F7: Accrual | G7: Depreciable
A8: Plumbing | B8: Plumbing | C8: 5 | D8: 8210-0600 | E8: 1225-0500 | F8: Accrual | G8: Depreciable
B9: Barriers | C9: 5 | D9: 8210-0600 | E9: 1225-0500 | F9: Accrual | G9: Depreciable
A10: Fire pumps | B10: Fire pumps | C10: 5 | D10: 8210-0600 | E10: 1225-0500 | F10: Accrual | G10: Depreciable
A11: Generators | B11: Generators | C11: 5 | D11: 8210-0600 | E11: 1225-0500 | F11: Accrual | G11: Depreciable
A12: Elevators | B12: Elevators | C12: 5 | D12: 8210-0600 | E12: 1225-0500 | F12: Accrual | G12: Depreciable
A13: FireExt | B13: Fire Extinguishers | C13: 5 | D13: 8210-0600 | E13: 1225-0500 | F13: Accrual | G13: Depreciable
A14: CCTV | B14: CCTV | C14: 5 | D14: 8210-0500 | E14: 1225-0400 | F14: Accrual | G14: Depreciable
A15: Comp | B15: Computers | C15: 3 | D15: 8210-0500 | E15: 1225-0400 | F15: Accrual | G15: Depreciable
A16: Servers | B16: Servers | C16: 3 | D16: 8210-0500 | E16: 1225-0400 | F16: Accrual | G16: Depreciable
A17: CellPh | B17: Cell phones | C17: 3 | D17: 8210-0500 | E17: 1225-0400 | F17: Accrual | G17: Depreciable
A18: IT Equip | B18: IT Equip | C18: 3 | D18: 8210-0500 | E18: 1225-0400 | F18: Accrual | G18: Depreciable
A19: F&F | B19: F&F | C19: 5 | D19: 8210-0300 | E19: 1225-0200 | F19: Accrual | G19: Depreciable
A20: Tools | B20: Tools | C20: 5 | D20: 8210-0700 | E20: 1225-0600 | F20: Accrual | G20: Depreciable
A21: LowCursy | B21: Low Current System | C21: 5 | D21: 8210-0700 | E21: 1225-0600 | F21: Accrual | G21: Depreciable
A22: Building
A23: Parking System
A24: NonDep | B24: NonDep | C24: 0 | D24: 8210-0600 | E24: 1225-0500 | G24: NonDepreciable

Sheet Asset Type
B1: Return
G2: Asset types control the default Asset account , depreciation group and also used for reporting
E3: For Asset Transactions
H4: GL Accounts
B5: Asset Type code | C5: Recovery Details (years) | D5: Asset type name | E5: Description | F5: Asset Depreciation Group | G5: Asset Code Prefix | H5: Asset Cost Account | I5: Disposition Account | J5: Accumulated Disposition | K5: Derecognition cost Account | L5: Derecognition - Acc Depr | M5: Asset Revaluation | N5: Revaluation Reserve | O5: Revaluation P&L | P5: Revaluation Surplus/Deficit
B6: HVACMec | D6: HVAC/Mechanical | E6: HVAC/Mechanical | F6: HVACMec | G6: HVACMec | H6: 1220-0500 | I6: 7260-1000 | J6: 1225-0500 | K6: 7260-1000 | L6: 1225-0500 | Q6: 8210-0200 | R6: PPE Dep - Building and Infrastructure
B7: Electrical | D7: Electrical | E7: Electrical | F7: Electrical | G7: ELE | H7: 1220-0500 | I7: 7260-1000 | J7: 1225-0500 | K7: 7260-1000 | L7: 1225-0500 | Q7: 8210-0300 | R7: PPE Dep - Furniture & Fixtures
B8: Plumbing | D8: Plumbing | E8: Plumbing | F8: Plumbing | G8: PLM | H8: 1220-0500 | I8: 7260-1000 | J8: 1225-0500 | K8: 7260-1000 | L8: 1225-0500 | Q8: 8210-0400 | R8: PPE Dep - Office Equipment
B9: Barriers | D9: Barriers | E9: Barriers | F9: Barriers | G9: BAR | H9: 1220-0500 | I9: 7260-1000 | J9: 1225-0500 | K9: 7260-1000 | L9: 1225-0500 | Q9: 8210-0500 | R9: PPE Dep - IT Hardware
B10: Fire pumps | D10: Fire pumps | E10: Fire pumps | F10: Fire pumps | G10: FRP | H10: 1220-0500 | I10: 7260-1000 | J10: 1225-0500 | K10: 7260-1000 | L10: 1225-0500 | Q10: 8210-0600 | R10: PPE Dep - Machinery & Equipment
B11: Generators | D11: Generators | E11: Generators | F11: Generators | G11: GEN | H11: 1220-0500 | I11: 7260-1000 | J11: 1225-0500 | K11: 7260-1000 | L11: 1225-0500 | Q11: 8210-0700 | R11: PPE Dep - Tools & Appliances
B12: Elevators | D12: Elevators | E12: Elevators | F12: Elevators | G12: ELV | H12: 1220-0500 | I12: 7260-1000 | J12: 1225-0500 | K12: 7260-1000 | L12: 1225-0500 | Q12: 8210-0800 | R12: PPE Dep - Motor Vehicles
B13: Fire Extuinguishers | D13: Fire Extuinguishers | E13: Fire Extuinguishers | F13: Fire Extuinguishers | G13: FRE | H13: 1220-0500 | I13: 7260-1000 | J13: 1225-0500 | K13: 7260-1000 | L13: 1225-0500 | Q13: 8210-0900 | R13: PPE Dep - Expensed assets
B14: CCTV | D14: CCTV | E14: CCTV | F14: CCTV | G14: CCV | H14: 1220-0400 | I14: 7260-1000 | J14: 1225-0400 | K14: 7260-1000 | L14: 1225-0400 | Q14: 8210-1000 | R14: PPE Dep - Other
B15: Computers | D15: Computers | E15: Computers | F15: Computers | G15: COM | H15: 1220-0400 | I15: 7260-1000 | J15: 1225-0400 | K15: 7260-1000 | L15: 1225-0400 | Q15: 8210-1400 | R15: IP Dep - Expensed Assets
B16: Servers | D16: Servers | E16: Servers | F16: Servers | G16: SER | H16: 1220-0400 | I16: 7260-1000 | J16: 1225-0400 | K16: 7260-1000 | L16: 1225-0400 | Q16: 1220-0100 | R16: PPE Cost - Building and Infrastructure
B17: Cell phones | D17: Cell phones | E17: Cell phones | F17: Cell phones | G17: PHN | H17: 1220-0400 | I17: 7260-1000 | J17: 1225-0400 | K17: 7260-1000 | L17: 1225-0400 | Q17: 1220-0200 | R17: PPE Cost - Furniture & Fixtures
... B19: F&F | D19: Furnitures and Fixtures | E19: Furnitures and Fixtures | F19: F&F | G19: FNF | H19: 1220-0200 | I19: 7260-1000 | J19: 1225-0200 | K19: 7260-1000 | L19: 1225-0200 | Q19: 1220-0400 | R19: PPE Cost - IT Hardware
B20: Building | D20: Building | E20: Building | F20: Building | G20: BUL | H20: 1220-0100 | J20: 1225-0100 | L20: 1225-0100 | Q20: 8210-0200 | R20: PPE Dep - Building and Infrastructure
B21: Parking System | D21: Parking System | E21: Parking System | F21: Parksys | G21: PSY
B24: Fan coil unit | D24: Fan coil unit | E24: Fan coil unit | F24: HVAC/Mechanical | G24: HVACMec | H24: 1220-0500 | I24: 7260-1000 | J24: 1225-0500 | K24: 7260-1000 | L24: 1225-0500
B25: Chilers | D25: Chilers | E25: Chilers | F25: HVAC/Mechanical | G25: HVACMec | H25: 1220-0500 | I25: 7260-1000 | J25: 1225-0500 | K25: 7260-1000 | L25: 1225-0500
B26: Chilled water pumps | D26: Chilled water pumps | E26: Chilled water pumps | F26: HVAC/Mechanical | G26: HVACMec | H26: 1220-0500 | I26: 7260-1000 | J26: 1225-0500 | K26: 7260-1000 | L26: 1225-0500
B27: Cooling tower | D27: Cooling tower | E27: Cooling tower | F27: HVAC/Mechanical | G27: HVACMec | H27: 1220-0500 | I27: 7260-1000 | J27: 1225-0500 | K27: 7260-1000 | L27: 1225-0500
B28: Dosing system | D28: Dosing system | E28: Dosing system | F28: HVAC/Mechanical | G28: HVACMec | H28: 1220-0500 | I28: 7260-1000 | J28: 1225-0500 | K28: 7260-1000 | L28: 1225-0500
B29: pressurization system | D29: pressurization system | E29: pressurization system | F29: HVAC/Mechanical | G29: HVACMec | H29: 1220-0500 | I29: 7260-1000 | J29: 1225-0500 | K29: 7260-1000 | L29: 1225-0500
B30: Fresh air handling unit | D30: Fresh air handling unit | E30: Fresh air handling unit | F30: HVAC/Mechanical | G30: HVACMec | H30: 1220-0500 | I30: 7260-1000 | J30: 1225-0500 | K30: 7260-1000 | L30: 1225-0500
B31: Air hauding unit | D31: Air hauding unit | E31: Air hauding unit | F31: HVAC/Mechanical | G31: HVACMec | H31: 1220-0500 | I31: 7260-1000 | J31: 1225-0500 | K31: 7260-1000 | L31: 1225-0500
B32: Life safety fan | D32: Life safety fan | E32: Life safety fan | F32: HVAC/Mechanical | G32: HVACMec | H32: 1220-0500 | I32: 7260-1000 | J32: 1225-0500 | K32: 7260-1000 | L32: 1225-0500
B33: Dx Unit | D33: Dx Unit | E33: Dx Unit | F33: HVAC/Mechanical | G33: HVACMec | H33: 1220-0500 | I33: 7260-1000 | J33: 1225-0500 | K33: 7260-1000 | L33: 1225-0500
B34: Package unit | D34: Package unit | E34: Package unit | F34: HVAC/Mechanical | G34: HVACMec | H34: 1220-0500 | I34: 7260-1000 | J34: 1225-0500 | K34: 7260-1000 | L34: 1225-0500
B35: Decoratiue unit | D35: Decoratiue unit | E35: Decoratiue unit | F35: HVAC/Mechanical | G35: HVACMec | H35: 1220-0500 | I35: 7260-1000 | J35: 1225-0500 | K35: 7260-1000 | L35: 1225-0500
... B47: Elevators | D47: Elevators | E47: Elevators | F47: Elevators | G47: ELV | H47: 1220-0500 | I47: 7260-1000 | J47: 1225-0500 | K47: 7260-1000 | L47: 1225-0500
B105: PM
B106: PM_HVAC | D106: PM_HVAC | E106: PM_HVAC/Mechanical | F106: NonDepreciable | G106: HVC | H106: 1220-0500 | I106: 7260-1000 | J106: 1225-0500 | K106: 7260-1000 | L106: 1225-0500 | Q106: 1220-0500 | R106: PPE Cost - Machinery & Equipment
B107: PM_Electrical | D107: PM_Electrical | E107: PM_Electrical | F107: NonDepreciable | G107: ELE | H107: 1220-0500 | I107: 7260-1000 | J107: 1225-0500 | K107: 7260-1000 | L107: 1225-0500 | Q107: 1220-0600 | R107: PPE Cost - Tools & Appliances
B108: PM_Plumbing | D108: PM_Plumbing | E108: Plumbing | F108: NonDepreciable | G108: PLM | H108: 1220-0500 | I108: 7260-1000 | J108: 1225-0500 | K108: 7260-1000 | L108: 1225-0500 | Q108: 1220-0700 | R108: PPE Cost - Motor Vehicles
B109: PM_Barriers | D109: PM_Barriers | E109: Barriers | F109: NonDepreciable | G109: BAR | H109: 1220-0500 | I109: 7260-1000 | J109: 1225-0500 | K109: 7260-1000 | L109: 1225-0500 | Q109: 1220-0800 | R109: PPE Cost - Expensed assets
B110: PM_Fire pumps | D110: PM_Fire pumps | E110: Fire pumps | F110: NonDepreciable | G110: FRP | H110: 1220-0500 | I110: 7260-1000 | J110: 1225-0500 | K110: 7260-1000 | L110: 1225-0500 | Q110: 1220-0900 | R110: PPE Cost - Other
B111: PM_Generators | D111: PM_Generators | E111: Generators | F111: NonDepreciable | G111: GEN | H111: 1220-0500 | I111: 7260-1000 | J111: 1225-0500 | K111: 7260-1000 | L111: 1225-0500 | Q111: 1220-9999 | R111: Total Property, Plant & Equipment - Cost
B112: PM_Elevators | D112: PM_Elevators | E112: Elevators | F112: NonDepreciable | G112: ELV | H112: 1220-0500 | I112: 7260-1000 | J112: 1225-0500 | K112: 7260-1000 | L112: 1225-0500 | Q112: 1225-0000 | R112: PPE Accumulated Depreciation
B113: PM_Fire Extuinguishers | D113: PM_Fire Extuinguishers | E113: Fire Extuinguishers | F113: NonDepreciable | G113: FRE | H113: 1220-0500 | I113: 7260-1000 | J113: 1225-0500 | K113: 7260-1000 | L113: 1225-0500 | Q113: 1225-0100 | R113: PPE Acc Dep - Building and Infrastructure
B114: PM_CCTV | D114: PM_CCTV | E114: CCTV | F114: NonDepreciable | G114: CCV | H114: 1220-0400 | I114: 7260-1000 | J114: 1225-0400 | K114: 7260-1000 | L114: 1225-0400 | Q114: 1225-0200 | R114: PPE Acc Dep - Furniture & Fixtures
B115: PM_Access Control | D115: PM_Access Control | E115: Access Control | F115: NonDepreciable | G115: ACC | H115: 1220-0400 | I115: 7260-1000 | J115: 1225-0400 | K115: 7260-1000 | L115: 1225-0400 | Q115: 1225-0300 | R115: PPE Acc Dep - Office Equipment
B116: PM_Water Tank | D116: PM_Water Tank | E116: WaterTank | F116: NonDepreciable | G116: WTC | H116: 1220-0500 | I116: 7260-1000 | J116: 1225-0500 | K116: 7260-1000 | L116: 1225-0500 | Q116: 1225-0400 | R116: PPE Acc Dep - IT Hardware
B117: PM_Vehicle | D117: PM_Vehicle | E117: Vehicle | F117: NonDepreciable | G117: VEH | H117: 1220-0200 | I117: 7260-1000 | J117: 1225-0200 | K117: 7260-1000 | L117: 1225-0200 | Q117: 1225-0500 | R117: PPE Acc Dep - Machinery & Equipment
... B119: PM_Servers | D119: PM_Servers | E119: Servers | F119: NonDepreciable | G119: SER | H119: 1220-0400 | I119: 7260-1000 | J119: 1225-0100 | K119: 7260-1000 | L119: 1225-0100 | Q119: 1225-0700 | R119: PPE Acc Dep - Motor Vehicles
B120: PM_Cell phones | D120: PM_Cell phones | E120: Cell phones | F120: NonDepreciable | G120: PHN | H120: 1220-0400 | I120: 7260-1000 | K120: 7260-1000 | Q120: 1225-0800 | R120: PPE Acc Dep - Expensed assets
B121: PM_IT Equip | D121: PM_IT Equip | E121: IT Equip | F121: NonDepreciable | G121: ITE | H121: 1220-0400 | I121: 7260-1000 | K121: 7260-1000
B122: PM_F&F | D122: PM_F&F | E122: Furnitures and Fixtures | F122: NonDepreciable | G122: FNF | H122: 1220-0200 | I122: 7260-1000 | K122: 7260-1000
B123: PM_Tools | D123: PM_Tools | E123: Tools | F123: NonDepreciable | G123: TOL | H123: 1220-0600 | I123: 7260-1000 | K123: 7260-1000
B124: PM_LowCurrent system | D124: PM_LowCurrent system | E124: Low Current system | F124: NonDepreciable | H124: 1220-0500 | I124: 7260-1000 | K124: 7260-1000

Sheet Asset Attachment type
A1: Return
A2: Asset Attachment types
B5: Object | C5: Attachment types
B6: Fixed Asset | C6: Warranty
B7: Fixed Asset | C7: Manuals
B8: Fixed Asset | C8: Supplier documents
B9: Fixed Asset | C9: Others

Sheet Assets Process
A1: Return
A4: They receive the full value of the whole building, including the value and cost of the all assets included in the building
A5: No Split or assets reigestered for the assets in the building
A6: FM will build the asset register for the handed over buildings and all the assets will be tagged under the nondeprciable group
A7: In case of new asset is added to the handed over building, they will be tagged under their respectvie depreciation group and deprciated as per schedule
A10: Will the building value get reduced by the value of the new added deprciated asset?
A11: The assets that are going to be under decprciated groups will be added to the system with their current value, and deprciation will be calculated from that point
A12: The value of the added assets will be deducted from the total building asset value
A13: Finance will be responsible to add and capitlize the new assets

Sheet Maintenance models
A1: Return
A3: Model | B3: In Scope (Y/N)
A4: In-house servicing | B4: Y
A5: 2. Outsourcing Model – Contractual Work | B5: Y
A6: 3. Outsourcing Model – Non‑Contractual Work | B6: Y
A7: 4. Out of Scope Work | B7: Y
A8: 5. Major WO | B8: Y
A11: Maintenance Models Overview
A13: 1. In‑House Servicing
A14: Process Step | B14: FM Team | C14: Vendor | D14: WO Status Lifecycle
A15: 1. Maintenance Request (WO) raised by any end-user under “General Maintenance” category | B15: - | C15: – | D15: Call
A16: 2. CAFM planner receives WO and updates unit, category, WO category and priority | B16: ✔️ | C16: – | D16: Call
A17: 3. CAFM Planner assigns supervisor/technicians | B17: ✔️ | C17: – | D17: Scheduled
A18: 4. Technicians visit site, identify materials required | B18: ✔️ | C18: – | D18: In Progress
A19: 5. Technicians add required materials or spare parts | B19: ✔️ | C19: – | D19: Material Required
A20: 6. Storekeeper releases the materials and quantity (Cost TBD) | B20: ✔️ | C20: – | D20: Material Released
A21: 7. Technician executes work and marks as "Ready to Close" | B21: ✔️ | C21: – | D21: Ready to Close
A22: 8. Supervisor reviews and closes work | B22: ✔️ | C22: – | D22: Work Completed
A23: Additional Statuses | D23: On-Hold, Cancelled, Request Reassignment, Reopened
A25: 2. Outsourcing Model – Contractual Work
A26: Process Step | B26: FM Team | C26: Vendor | D26: WO Status Lifecycle
A27: 1. Maintenance Request (WO) raised by any end-user under “General Maintenance” category | B27: ✔️ | C27: – | D27: Call
A28: 2. CAFM planner receives WO and updates unit, category, WO category and priority | B28: ✔️ | C28: – | D28: Scheduled
A29: 3. FM Manager/Technician tags equipment and assigns to SC Vendor | B29: ✔️ | C29: – | D29: Assigned to Vendor
A30: 4. Vendor Performs work & submits job completion report to FM | B30: – | C30: ✔️ | D30: Vendor Completed
A31: 7. FM Manager reviews work, attaches job completion report, marks WO completed | B31: ✔️ | C31: – | D31: Work Completed
A32: Additional Statuses | D32: On‑Hold, Cancelled, Reopened
A35: 3. Outsourcing Model – Non‑Contractual Work
A36: Process Step | B36: FM Team | C36: Vendor | D36: WO Status Lifecycle
A37: 1. Maintenance Request (WO) raised by any end-user under “General Maintenance” category | B37: ✔️ | C37: – | D37: Call
A38: 2. CAFM planner receives WO and updates unit, category, WO category and priority | B38: ✔️ | C38: – | D38: Scheduled
A39: 3. Supervisor/Technician goes on site and tags equipment, and get vendor quotations | B39: ✔️ | C39: – | D39: Awaiting Vendor Quotation
A40: 4. Vendor(s) submits quotation to supervisor | B40: - | C40: ✔️ | D40: Vendor Quoation Submitted
A41: 5. FM Manager/Technician selects winning vendor | B41: ✔️ | C41: – | D41: Vendor Assigned
A42: 6. Vendor Performs work & submits job completion report to FM | B42: – | C42: ✔️ | D42: Vendor Completed
A43: 7. FM Manager reviews work, attaches job completion report, marks WO completed | B43: ✔️ | C43: - | D43: Work Completed
A44: Additional Statuses | D44: On‑Hold, Cancelled, Reopened
A47: 4. Out of Scope Work
A48: Process Step | B48: FM Team | C48: Vendor | D48: WO Status Lifecycle
A49: 1. Maintenance Request (WO) raised by any end-user under “General Maintenance” category | B49: ✔️ | C49: – | D49: Call
A50: 2. CAFM planner receives WO and updates unit, category, WO category and priority | B50: ✔️ | C50: – | D50: Scheduled
A51: 3. Out-of-scope work identified | B51: ✔️ | C51: – | D51: On Hold → Out of Scope
A52: 4. Waseef sends quotation to Naufar for approval | B52: ✔️ | C52: – | D52: On Hold → Waiting Naufar Approval
A53: 3. Naufar reviews and either: | B53: ✔️ | C53: – | D53: -
A54: • Assigns work directly to Waseef – PR raised, Job completion report required | B54: ✔️ | C54: – | D54: 1. In‑House Servicing
A55: • Raises PR through procurement for market review | B55: ✔️ | C55: – | D55: 3. Outsourcing Model – Non‑Contractual Work
A58: 5. Major WO
A59: Process Step | B59: Naufar | C59: Waseef | D59: Vendor | E59: WO Status Lifecycle
A60: 1. End‑user contacts the CAFM Planner to request a Facility Change Request (FCR) | B60: ✔️ | D60: – | E60: Call
A61: 2. CAFM Planner creates the Work Order (WO) and updates the unit, FCR category, subcategory, and priority | B61: - | C61: ✔️ | D61: – | E61: Call
A62: 3. CAFM Planner assigns the Work Order to the Supervisor | B62: - | C62: ✔️ | D62: – | E62: Scheduled
A63: 4. Supervisor visits the site, identifies end‑user requirements, and completes the FCR form. | B63: - | C63: ✔️ | D63: – | E63: In Progress
A64: 5. Supervisor enters the full proposal information into the FCR custom table and sends it to the end‑user for approval | B64: - | C64: ✔️ | D64: – | E64: Approval Process
A65: 6. End‑user forwards the FCR to their Department Manager | B65: ✔️ | C65: - | D65: –
A66: 7. Department Manager forwards the FCR to FM team and processes it through the workflow: | B66: ✔️ | C66: - | D66: –
A67: • FM Engineer | B67: ✔️ | C67: - | D67: –
A68: • FM Senior Engineer | B68: ✔️ | C68: - | D68: –
A69: • Project Manager | B69: ✔️ | C69: - | D69: –
A70: • Facility Director | B70: ✔️ | C70: - | D70: –
A71: • Assistant COO | B71: ✔️ | C71: - | D71: –
A72: • COO | B72: ✔️ | C72: - | D72: –
A73: 8. Once approved it goes to supervisor to submits Scope of Work (SoW) to the FM team. | B73: - | C73: ✔️ | D73: – | E73: SoW Preparation
A74: 9. FM Senior Engineer decides one of the following actions: | B74: ✔️ | D74: –
A75: • Assign work directly to Waseef (PR raised; Job Completion Report required) | B75: - | C75: - | D75: – | E75: 1. In‑House Servicing
A76: • Raise a PR through Procurement for market review and assign external vendor | B76: ✔️ | D76: ✔️ | E76: 3. Outsourcing Model – Non‑Contractual Work
A79: 6. Work Permit
A80: Process Step | B80: Waseef | C80: WO Status Lifecycle
A81: 1. FM team communicate with the HSE officer for Work Permit under 'Work Permit' category and sub-category | B81: ✔️ | C81: Call
A82: 2. HSE will update the Work Permit Custom table and update due date as the work permit expiry | B82: ✔️ | C82: In Progress
A83: 3. Issue the work permit | B83: ✔️ | C83: Work Permit Issued
A84: 4. Mark the WO as completed on or before the due date | B84: ✔️ | C84: Work Completed
A85: 5. if WO is overdue, to be tracked unit it is closed | B85: ✔️ | C85: -

Sheet Team Structure
A1: Return
A2: Team Structure
A3: Team | B3: Role Category | C3: Position
A4: Naufar | B4: Management | C4: Facility Director
C5: Project Manager
B6: Senior Level | C6: Senior Engineer
B7: Engineering | C7: FM Engineer – Electrical
C8: FM Engineer – ELV
C9: FM Engineer – Mechanical
A10: FM Service Provider | B10: Site Management/ Adminstration | C10: FM Manager
B11: Engineering | C11: FM Engineer – ELV
C12: FM Engineer – Electrical
C13: FM Engineer – HVAC & Mechanical
C14: FM Engineer – Biomedical
B15: Supervision | C15: Supervisor – HVAC
C16: Supervisor – Electrical
C17: Supervisor – Mechanical
C18: Supervisor – Civil
C19: Supervisor – Landscaping
B20: CAFM | C20: CAFM Planners
B21: Technical | C21: Technician – HVAC
C22: Technician – Electrical
C23: Technician – Mechanical
C24: Technician – Civil
C25: Technician – Landscaping
C26: Technician – ELV
B27: Support | C27: Storekeeper
B28: HSE | C28: HSE Officer
B29: Administration | C29: FM Admin – Document Controller

Sheet Employee Work slots
A1: Return
A2: Employee work slots
A4: Days of the Week
A6: Day of Week | B6: Start Time | C6: End Time
A7: all 7 days | B7: 12h00 | C7: 23h59
A15: Slot | B15: From time | C15: To Time
A16: Day shift | B16: 07-AM | C16: 07-PM
A17: Night shift | B17: 07-PM | C17: 07-AM

Sheet WO Priority
A1: Return
A2: 1 | B2: Work Order Setup
A4: 1.01 | B4: WO Priority (for configuration) | C4: Remarks | D4: Colour Preference on Tech Mobile?
A5: 1 | B5: P1 - Emergency | C5: Critical | D5: Red
A6: 2 | B6: P2 - Urgent | C6: High | D6: Orange
A7: 3 | B7: P3 - High | C7: Medium | D7: Green
A8: 4 | B8: P4 – Routine | C8: PPM | D8: Orange/Yellow
A9: 5 | B9: P5 - Low | C9: Low | D9: Blue

Sheet WO Status and Change Reason
A1: Return
A2: 1 | B2: Work Order Setup
A5: 1.02 | B5: WO Standard Status in Yardi
C6: Status | D6: Type (standard/custom) | E6: Commercial Café Status name | F6: Commercial Café Email Yes/No
C7: Call | D7: Standard | E7: General Maintenance Request
C8: Web | D8: Standard | E8: General Maintenance Request
C9: Scheduled | D9: Standard | E9: In Progress
C10: In Progress | D10: Standard | E10: In Progress
C11: Work Completed | D11: Standard | E11: Completed | F11: Yes
C12: Cancelled | D12: Standard | E12: Cancelled | F12: Yes
C13: On Hold | D13: Standard | E13: On Hold
C14: Awaiting Quotation | D14: Custom | E14: In Progress
C15: Quotation submitted | D15: Custom | E15: In Progress
C16: Quotation Approval | D16: Custom | E16: In Progress
C17: Quotaiton Approval | D17: Custom | E17: In Progress
C18: Quotation Approved | D18: Custom | E18: In Progress
C19: Procurement Review | D19: Custom | E19: In Progress
C20: Procurement Review | D20: Custom | E20: In Progress
C21: Assigned for Work | D21: Custom | E21: In Progress
C22: In Progress | D22: Custom | E22: In Progress
C23: Vendor Completed | D23: Custom | E23: Completed
C24: Vendor Onboarding | D24: Custom
A26: 1.03 | B26: WO Status Change Reason | C26: Status | D26: Reason
C27: On Hold | D27: Awaiting quotation
D28: Awaiting Approvals
D29: Awaiting FM/PM feedback
D30: Tenant/Access not available
D31: Awaiting Materials
D32: Requires Specialized Skill
D33: Material Out of stock
D34: Awaiting vendor schedule
D35: Under verification
C36: Cancelled
D37: Under Warranty
D38: Duplicate WO
C39: Request Re-assignment | D39: Requires vendor replacement

Sheet WO Matrix
A1: Return
A2: 1.04 | B2: WO Category | C2: Category | D2: AMC (Yes/No) | E2: Commercial Café Category name
C3: HVAC | D3: Yes | E3: HVAC
C4: Fire Life Safety | D4: Yes | E4: Fire Life Safety
C5: Soft Services | D5: Yes | E5: Soft Services
C6: Civil | D6: Yes | E6: Civil
C7: Electical | D7: Yes | E7: Electical
C8: Plumbing | D8: Yes | E8: Plumbing
C9: Security System | D9: No | E9: Security System
C10: Mechanical | D10: Yes | E10: Mechanical
C11: Elevator | D11: Yes | E11: Elevator & Escalator
C12: Vertical Transport | D12: No | E12: Vertical Transport
C13: LPG Systems | D13: No | E13: LPG Systems
C14: Parking Management System | D14: No | E14: Parking Management System
... C21: HOSPY | D21: Yes | E21: Laundry & Kitchen Equipments
A24: 1.05 | B24: WO Subcategory | C24: Category | D24: SubCategory | E24: Remarks
C25: WO_Category.HVAC | D25: AHU
C26: WO_Category.HVAC | D26: FCU
C27: WO_Category.HVAC | D27: VAV
C28: WO_Category.HVAC | D28: FAHU
C29: WO_Category.HVAC | D29: Cooling Tower
C30: WO_Category.HVAC | D30: Chillers
C31: WO_Category.HVAC | D31: Window AC
C32: WO_Category.HVAC | D32: Split AC
C33: WO_Category.HVAC | D33: Package Unit AC
C34: WO_Category.HVAC | D34: Spilit Duct AC
C35: WO_Category.HVAC | D35: Exhaust/Ventilation
C36: WO_Category.HVAC | D36: Heat exchanger
... C50: WO_Category.HVAC | D50: Others
C51: WO_Category.HVAC | D51: Smoke Extract Fans | E51: new added
C52: WO_Category.HVAC | D52: Humidifiers & Dehumidifiers | E52: Important for climate control in Hospitals
C53: WO_Category.HVAC | D53: UV Air Purification Systems | E53: Used in HVAC for better air quality.
C54: WO_Category.HVAC | D54: Air cuirtain
C55: WO_Category.Civil | D55: Painting
C56: WO_Category.Civil | D56: Flooring
C57: WO_Category.Civil | D57: Demolishing
C58: WO_Category.Civil | D58: Fitting
C59: WO_Category.Civil | D59: Ceiling
C60: WO_Category.Civil | D60: Carpet repairs/replacement
C61: WO_Category.Civil | D61: Keys & Locks
C62: WO_Category.Civil | D62: Furniture Repairs
C63: WO_Category.Civil | D63: Fixtures Repairs
C64: WO_Category.Civil | D64: Glass Replacement /Repairs
C65: WO_Category.Civil | D65: Tiling and Grouting
... C68: WO_Category.Civil | D68: Signage Rectifications
C69: WO_Category.Civil | D69: Expansion Joints | E69: new added
C70: WO_Category.Civil | D70: Curtain Walls & Cladding | E70: new added
C71: WO_Category.Civil | D71: Canopies & Awnings | E71: new added
C72: WO_Category.Civil | D72: Concrete Repairs | E72: new added
C73: WO_Category.Civil | D73: Others
C74: WO_Category.Electrical | D74: Light
C75: WO_Category.Electrical | D75: Emergency Light System
C76: WO_Category.Electrical | D76: Generators
C77: WO_Category.Electrical | D77: Electric Motors
C78: WO_Category.Electrical | D78: Power Supply
C79: WO_Category.Electrical | D79: Main Distribution Board
C80: WO_Category.Electrical | D80: Capacitor Banks
C81: WO_Category.Electrical | D81: UPS
C82: WO_Category.Electrical | D82: VFD
C83: WO_Category.Electrical | D83: Energy monitoring
C84: WO_Category.Electrical | D84: Lighting Control System
... C95: WO_Category.Electrical | D95: Sliding doors
C96: WO_Category.Electrical | D96: Earthing & Lightning Protection | E96: new added
C97: WO_Category.Electrical | D97: Busbars | E97: new added
C98: WO_Category.Electrical | D98: External & Landscape Lighting | E98: new added
C99: WO_Category.Plumbing | D99: Water supply
C100: WO_Category.Plumbing | D100: Drainage
C101: WO_Category.Plumbing | D101: Kitchen Drain
C102: WO_Category.Plumbing | D102: Grease Trap
C103: WO_Category.Plumbing | D103: Water features
C104: WO_Category.Plumbing | D104: Sanitary and fittings
C105: WO_Category.Plumbing | D105: Others
C106: WO_Category.Plumbing | D106: Water tank and cleaning
C107: WO_Category.Plumbing | D107: Sump pit
C108: WO_Category.Plumbing | D108: Irrigation
C109: WO_Category.Plumbing | D109: Grey water system
C110: WO_Category.Plumbing | D110: Water filtration
... C137: WO_Category.Fire Life Safety | D137: Central Battery System
C138: WO_Category.Fire Life Safety | D138: Emergency Evacuation System | E138: new added
C139: WO_Category.Fire Life Safety | D139: Fire Blankets | E139: new added
C140: WO_Category.Fire Life Safety | D140: fire extinguisher | E140: new added
C141: WO_Category.Fire Life Safety | D141: Fire Alarm Interfacing | E141: new added
C142: WO_Category.Fire Life Safety | D142: Others
C143: WO_Category.LPG Systems | D143: LPG Tank
C144: WO_Category.LPG Systems | D144: LPG Detection system
C145: WO_Category.LPG Systems | D145: LPG Piping
C146: WO_Category.LPG Systems | D146: LPG Meter
C147: WO_Category.LPG Systems | D147: Emergency Shut-Off Valves | E147: new added
C148: WO_Category.LPG Systems | D148: Others
C149: WO_Category.Parking Management System | D149: Exit Gate Barrier
C150: WO_Category.Parking Management System | D150: Ticketing Machine
C151: WO_Category.Parking Management System | D151: Entrance Gate Barrier
C152: WO_Category.Parking Management System | D152: Pay station
C153: WO_Category.Parking Management System | D153: Mobile pay machine
C154: WO_Category.Parking Management System | D154: Reflector Mirror
C155: WO_Category.Parking Management System | D155: Speed Humps
C156: WO_Category.Parking Management System | D156: Directional Signages
C157: WO_Category.Parking Management System | D157: Directional Lights
C158: WO_Category.Parking Management System | D158: Height limit barrier
C159: WO_Category.Parking Management System | D159: EV Charging Stations | E159: new added
...

Sheet Employee Skills
A1: Return
A3: 1.11 | B3: Skills
B5: Skill code | C5: Skill name | D5: Pay amount | E5: Bill amount | F5: Property
B6: SGD | C6: Security Guard | E6: 0 | F6: .all
B7: ACC | C7: AC Craftworker | E7: 0 | F7: .all
B8: ACT | C8: AC Technician | E8: 0 | F8: .all
B9: ADRENG | C9: Agricultural Engineer | E9: 0 | F9: .all
B10: AACT | C10: Assistant AC Technician | E10: 0 | F10: .all
B11: AMC | C11: Assistant Mason Craftworker | E11: 0 | F11: .all
B12: AP | C12: Assistant Painter | E12: 0 | F12: .all
B13: AT | C13: Assistant Technician | E13: 0 | F13: .all
B14: ASPT | C14: Assistant Swimming Pool Technican | E14: 0 | F14: .all
B15: AWF | C15: Assistant Welder & Fabricator | E15: 0 | F15: .all
B16: CAHKSUP | C16: Camp Administrator & HK Supervisor | E16: 0 | F16: .all
B17: CC | C17: Carpenter Craftworker | E17: 0 | F17: .all
... B44: HKT | C44: Housekeeping teamleader | E44: 0 | F44: .all

Sheet WO Attachments Types
A1: Return
B2: WO Attachments Types
B3: Quotations
B4: Works Completion Certificates
B5: Material Delivery Note
B6: PM Service Report
B7: Incident Reports
B8: Email Approval
B9: Technical/Inspection Reports
B10: Scope of Work Form
B11: Others
B12: Third Party Sevice Report
B13: Warranty Certificate

Sheet WO SLA KPI and Due Date Default
A1: Return
B2: Work Order Setup
B4: SLA Setup (KPI) | C4: Provide for each property, Category and priority combination
B6: Property | C6: WO Category | D6: Priority | E6: Response (Any status other than Call or Work Completed) | F6: Completion (Status = Work Completed) | G6: Duration includes After Office and Weekends?
B7: Naufar | D7: P1 - Emergency | E7: 0.30 Hours | F7: 4 Hours | G7: Yes
B8: Naufar | D8: P2 - Urgent | E8: 1 Hour | F8: 12 Hours | G8: Yes
B9: Naufar | D9: P3 - High | E9: 8 Hour | F9: 48 Hours | G9: Yes
B10: Naufar | D10: P4 – Routine | E10: 48 Hour | F10: 720 Hours | G10: Yes
B11: Naufar | D11: P5 - Low | E11: 48 Hour | F11: 720 Hours | G11: Yes
B12: Populate Due date based on SLA | C12: Completion
B13: Note: WO Completion SLA is computed from WO Creation date until the date when WO status is updated to Work Completed. There is no provision to exclude time spent on interim statuses like "On Hold", Awaiting Materials etc.

Sheet WO Workflows
A1: Return
A3: Facility Management and Operations Department Roles
A4: All roles which are required for WO Workflow needs to be listed
A6: Department | B6: Role
B7: Department Manager
B8: FM Engineer
B9: FM Senior Engineer
B10: Project Manager
B11: Facility Director
B12: Assistant COO
B13: COO
B14: Supervisor
A16: FCR Proposal
A17: Workflow Step | B17: Step Type | C17: Responsible Role | D17: Next Step (Approval / Modification / Rejection)
A18: New FCR Proposal | B18: In Process | C18: Originator | D18: Department Manager Review
D19: Modification Required
D20: Approved
D21: Rejected
A22: Department Manager Review | B22: In Process | C22: Department Manager | D22: FM Engineer Review
D23: Modification Required
D24: Approved
D25: Rejected
A26: FM Engineer Review | B26: In Process | C26: FM Engineer | D26: FM Senior Engineer Review
D27: Modification Required
D29: Rejected
A30: FM Senior Engineer Review | B30: In Process | C30: FM Senior Engineer | D30: Project Manager Review
D31: Modification Required
D32: Approved
D33: Rejected
A34: Project Manager Review | B34: In Process | C34: Project Manager | D34: Facility Director Review
D35: Modification Required
D36: Approved
D37: Rejected
A38: Facility Director Review | B38: In Process | C38: Facility Director | D38: Assistant COO Review
D39: Modification Required
D40: Approved
D41: Rejected
A42: Assistant COO Review | B42: In Process | C42: Assistant COO | D42: COO Review
D43: Modification Required
D44: Approved
D45: Rejected
A46: COO Review | B46: In Process | C46: COO | D46: Scope of Work (SoW) Submit
D47: Modification Required
D48: Approved
D49: Rejected
A50: Scope of Work (SoW) Submit | B50: In Process | C50: Supervisor | D50: Approved, SoW Submitted
D51: Modification Required
D52: Approved
D53: Rejected
A54: Approved, SoW Submitted | B54: Completion
A55: Rejected | B55: Reject
A56: Modification Required | B56: In Process | C56: Originator | D56: Department Manager Review
A60: FA Transfer
A61: Workflow Step | B61: Step Type | C61: Responsible Role | D61: Next Step (Approval / Modification / Rejection)
A63: New FA Transfer Ruquest | B63: In Process | C63: Originator | D63: Update FA Transfer Form
A64: Update FA Transfer Form | B64: In Process | C64: Originator | D64: Department Manager Review
D65: Modification Required
D66: Approved
D67: Rejected
A68: Request end-user approval | B68: In Process | C68: Department Manager | D68: Department Manager Review
D69: Modification Required
D70: Approved
D71: Rejected
A72: Department Manager Review | B72: In Process | C72: Department Manager | D72: FM Engineer Review
D73: Modification Required
D74: Approved
D75: Rejected
A76: FM Engineer Review | B76: In Process | C76: FM Engineer | D76: FM Senior Engineer Review
D77: Modification Required
D78: Approved
D79: Rejected
A80: FM Senior Engineer Review | B80: In Process | C80: FM Senior Engineer | D80: Project Manager Review
D81: Modification Required
D82: Approved
D83: Rejected
A84: Project Manager Review | B84: In Process | C84: Project Manager | D84: Facility Director Review
D85: Modification Required
D86: Approved
D87: Rejected
A88: Facility Director Review | B88: In Process | C88: Facility Director | D88: Send for Finance Review
D89: Modification Required
D90: Approved
D91: Rejected
A92: Send for Finance Review | B92: In Process | C92: Finance Review | D92: Approved, Transfer FA
A93: Approved, Transfer FA | B93: In Process
A95: Approved | B95: Completion
A96: Rejected | B96: Reject
A97: Modification Required | B97: In Process | C97: Originator | D97: Department Manager Review

Sheet WO Config Points 
A1: Return
B2: WO Setup
B3: Overall Result Validation
B4: Cannot pass if any detail fails | C4: No
B5: Cannot pass if a work order has been created | C5: No
B6: Cannot set if any detail does not have a result | C6: No
B9: Failed Details Validation
B10: Require a note | C10: Yes
B11: Require a photo | C11: Yes
B12: Require a work order | C12: No

Sheet Inspection Process
A1: Return
A2: Inspection Process
A3: Patient Move-Out Process
A4: Step | B4: Activity | C4: Responsible Party
A5: 1 | B5: Patient moves out and returns access items | C5: GRO / Patient
A6: 2 | B6: Send move-out notification email | C6: GRO
A7: 3 | B7: Create inspection request | C7: CAFM Planner
A8: 4 | B8: Update unit status (pre-inspection) | C8: CAFM Planner
A9: 5 | B9: Perform unit inspection | C9: Inspector
A10: 6 | B10: Upload photos and notes | C10: Inspector
A11: 7 | B11: Create Work Orders for snags | C11: Inspector / CAFM Planner
A12: 8 | B12: Process out-of-scope issues | C12: CAFM Planner
A13: 9 | B13: Execute and verify work | C13: Technician
A14: 10 | B14: Update unit status (post-work) | C14: CAFM Planner
A15: 11 | B15: Notify GRO and share reports | C15: CAFM Planner
A17: Incident Recording Process
A18: Step | B18: Activity | C18: Responsible Party
A19: 1 | B19: Report incident | C19: End User
A20: 2 | B20: Create incident inspection request | C20: CAFM Planner
A21: 3 | B21: Visit site and inspect | C21: Technician
A22: 4 | B22: Create snagging Work Order | C22: Technician
A23: 5 | B23: Notify FM team | C23: CAFM Planner
A25: Utility Inspection
A26: Step | B26: Activity | C26: Responsible
A27: 1 | B27: Schedule recurring inspections | C27: CAFM Planner
A28: 2 | B28: Perform meter readings (Electricity, Water, Irrigation, TSE, Tank Levels) | C28: Technician
A29: 3 | B29: Review and report | C29: CAFM Planner

Sheet PM Statuses
A1: Return
B2: PPM Standard Status in Yardi
B4: Status | C4: Type (standard/custom)
B5: Call | C5: Standard
B6: Scheduled | C6: Standard
B7: In Progress | C7: Standard
B8: Work Completed | C8: Standard
B9: Cancelled | C9: Standard
B10: On Hold | C10: Standard
C11: Custom
C12: Custom
C13: Custom
C14: Custom
C15: Custom
C16: Custom
C17: Custom
B18: Assigned for Work | C18: Custom
B19: In Progress | C19: Custom
B22: PPM Status Change Reason
B23: Status | C23: Reason
B24: On Hold | C24: Awaiting quotation
C25: Awaiting Approvals
C26: Awaiting FM/PM feedback
C27: Tenant/Access not available
C28: Awaiting Materials
C29: Requires Specialized Skill
C30: Material Out of stock
C31: Awaiting vendor schedule
C32: Under Verification
B33: Cancelled
B34: Request Re-assignment

Sheet PPM Process 
A1: Return
B2: PPM Process
B3: Step | C3: Activity | D3: In-house Process | E3: AMC Vendor Process
B4: 1 | C4: Create Equipment Templates | D4: FM Manager creates templates including PPM checklists, frequency, and readings | E4: FM Manager creates templates including PPM checklists, frequency, and readings
B5: 2 | C5: Create Equipment Records | D5: FM Manager creates equipment records or imports via template | E5: FM Manager creates equipment records or imports via template
B6: 3 | C6: PM Scheduling | D6: PMs are automatically generated as per schedule (daily automated task after office hours) | E6: PMs are automatically generated as per schedule (daily automated task after office hours)
B7: 4 | C7: PM Assignment | D7: PMs are auto-assigned to FM Manager based on assignment rules | E7: PMs are auto-assigned to Service Provider based on assignment rules
B8: 5 | C8: Perform PM Inspection | D8: FM Manager performs PM inspection and snagging | E8: Service Provider performs PM, completes checklist, uploads photos and evidence
B9: 6 | C9: Handle In-Scope Snags | D9: FM Manager raises WO for rectification | E9: Service Provider fixes snags within service contract scope
B10: 7 | C10: Handle Out-of-Scope Snags | D10: FM Manager raises WO for rectification | E10: Service Provider raises WO for snags outside service contract scope
B11: 8 | C11: Update PM Status | D11: FM Manager updates PM as completed after inspection | E11: Service Provider updates PM status to Completed
B12: 9 | C12: Work Order Processing | D12: All WOs follow the finalized Reactive Work Order process | E12: All WOs follow the finalized Reactive Work Order process

Sheet Inspection Statuses
A1: Return
B2: Inspection Standard Status in Yardi
B4: Status | C4: Type (standard/custom)
B5: Call | C5: Standard
B6: Scheduled | C6: Standard
B7: In Progress | C7: Standard
B8: Work Completed | C8: Standard
B9: Cancelled | C9: Standard
B10: On Hold | C10: Standard
C11: Custom
C12: Custom
C13: Custom
C14: Custom
C15: Custom
C16: Custom
C17: Custom
B18: Assigned for Work | C18: Custom
B19: In Progress | C19: Custom
B22: Inspection Status Change Reason
B23: Status | C23: Reason
B24: On Hold | C24: Awaiting quotation
C25: Awaiting Approvals
C26: Awaiting FM/PM feedback
C27: Tenant/Access not available
C28: Awaiting Materials
C29: Requires Specialized Skill
C30: Material Out of stock
C31: Awaiting vendor schedule
C32: Under Verification
B33: Cancelled
B34: Request Re-assignment

Sheet Inspections & PPM Config Points
A1: Return
B2: Inspections Setup | F2: PPM Setup
B4: Overall Result Validation | F4: Overall Result Validation
B5: Cannot pass if any detail fails | C5: No | F5: Cannot pass if any detail fails | G5: No
B6: Cannot pass if a work order has been created | C6: No | F6: Cannot pass if a work order has been created | G6: No
B7: Cannot set if any detail does not have a result | C7: No | F7: Cannot set if any detail does not have a result | G7: No
B10: Failed Details Validation | F10: Failed Details Validation
B11: Require a note | C11: Yes | F11: Require a note | G11: Yes
B12: Require a photo | C12: Yes | F12: Require a photo | G12: Yes
B13: Require a work order | C13: No | F13: Require a work order | G13: No

Sheet Auto Assignment rules
A1: Return
A2: Auto Assignment Rules
A3: Auto Assignment for Work Orders
A5: Legal Entity | B5: Property Code | C5: Property Name | D5: WO Category | E5: WO Auto Assigned to
D6: HVAC | E6: Supervisor
D7: Fire Life Safety | E7: Supervisor
D8: Soft Services | E8: Supervisor
D9: Civil | E9: Supervisor
D10: Electical | E10: Supervisor
D11: Plumbing | E11: Supervisor
D12: Security System | E12: Supervisor
D13: Mechanical | E13: Supervisor
D14: Vertical Transport | E14: Supervisor
D15: LPG Systems | E15: Supervisor
D16: Parking Management System | E16: Supervisor
D17: Meter Reading | E17: Supervisor
... D24: Hygene Services | E24: Supervisor
A26: Auto Assignment for PMs
A28: Legal Entity | B28: Property Code | C28: Property Name | D28: Equipment System | E28: Equipment type | F28: PM Auto Assigned To
A48: Auto Assignment for PMs
A50: Legal Entity | B50: Property Code | C50: Property Name | D50: Inspection type | E50: Inspection Template name | F50: PM Auto Assigned To
A51: Naufar | C51: .all | D51: Site Visit | E51: Site Visit | F51: Service Provider name
A52: Naufar | C52: .all | D52: Reinstatement | E52: Reinstatement | F52: Service Provider name
A53: Naufar | C53: .all | D53: Incident Reporting | E53: Incident Reporting | F53: FM Manager
A54: Naufar | C54: .all | D54: Preventive Maintenance | E54: Preventive Maintenance | F54: FM Manager
A55: Naufar | C55: .all | D55: Compliance Inspection | E55: Compliance Inspection | F55: Health and safety manager
A56: Naufar | C56: .all | D56: Hygiene & Cleaning Inspection | E56: Hygiene & Cleaning Inspection | F56: soft services manager
A57: Naufar | C57: .all | D57: Safety Audit | E57: Safety Audit | F57: Health and safety manager
A58: Naufar | C58: .all | D58: Security Inspection | E58: Security Inspection | F58: security manager
A59: Naufar | C59: .all | D59: Environmental Audit | E59: Environmental Audit | F59: Health and safety manager
A60: Naufar | C60: .all | D60: System Audits | E60: System Audits | F60: FM Manager
A61: Naufar | C61: .all | D61: Statutory Inspection | E61: Statutory Inspection | F61: leasing manager
A62: Naufar | C62: .all | D62: Performance Testing | E62: Performance Testing | F62: Hospital manager
... A65: Naufar | C65: .all | D65: System Integration Testing | E65: System Integration Testing | F65: FM Manager

Sheet Equipments Systems and Types
A1: Return | B1: ETL
A2: Equipment setup
A4: Equipment Systems
A5: Name | B5: Description
A6: HVAC | B6: Health, Safety, and Environment System
A7: Fire Life Safety | B7: Pest Control System
A8: Soft Services | B8: Cleaning System
A9: Civil | B9: Housekeeping System
A10: Electical | B10: Plumbing System
A12: Equipment Types
A13: Name | B13: Description
A14: AHU | B14: AHU
A15: FCU | B15: FCU
A16: VAV | B16: VAV
A17: FAHU | B17: FAHU
A18: Cooling Tower | B18: Cooling Tower
A19: Chillers | B19: Chillers
A20: Window AC | B20: Window AC
A21: Split AC | B21: Split AC
A24: UDF Equipments
A25: Max Hours
A26: Hours Consumed

Sheet PPM Checklists
A1: Return | B1: ETL

Sheet Equipments
A1: Return | B1: ETL
A2: Name | B2: EquipmentTemplateName | C2: Description | D2: ParentEquipmentName | E2: PropertyCode | F2: BuildingCode | G2: FloorCode | H2: UnitCode | I2: LocationCode | J2: EquipmentSystemName | K2: EquipmentTypeName | L2: Serial | M2: Manufacturer | N2: Model | O2: FixedAssetCode | P2: StartDate | Q2: PurchaseDate | R2: PurchasePrice | S2: InstalledDate | T2: ReplacementDate | U2: ReplacementCost | V2: Life | W2: UserDefinedField1 | X2: UserDefinedField2 | Y2: UserDefinedField3 | Z2: UserDefinedField4 | AA2: UserDefinedField5 | AB2: UserDefinedField6 | AC2: UserDefinedField7 | AD2: UserDefinedField8 | AE2: UserDefinedField9 | AF2: UserDefinedField10 | AG2: UserDefinedField11 | AH2: UserDefinedField12 | AI2: UserDefinedField13 | AJ2: UserDefinedField14 | AK2: UserDefinedField15 | AL2: UserDefinedField16 | AM2: Barcode | AN2: Notes | AO2: PositionNameOverride | AP2: EmployeeCodeOverride
A3: DAM-MEP-005 | C3: Irrigation controller-Basement 1 | E3: Naufar HILLS (2) - COMMUNITY CENTER Hospital | G3: Basement 1 | H3: DM2_BASE1 | J3: Landscaping | K3: Landscaping

Sheet Inspection checklists
A1: Return | B1: ETL

Sheet Warehouse Location
A1: Return | B1: ETL
A2: naufar

Sheet Item Categories
A1: Return | B1: ETL
A2: Code | B2: Description
A4: IN0001 | B4: Carpentry
A5: IN0002 | B5: Cleaning Chemicals
A6: IN0003 | B6: Cleaning Disposable
A7: IN0004 | B7: Cleaning Equipment
A8: IN0005 | B8: Cleaning Tools
A9: IN0006 | B9: Electrical
A10: IN0007 | B10: Painting
A11: IN0008 | B11: Hardware
A12: IN0009 | B12: HVAC
A13: IN0010 | B13: Kitchen Appliances
... A49: IN0046 | B49: Lighting

Sheet Item Type
A1: Return | B1: ETL
A2: Item Code | B2: Item Name | C2: Item Category
A3: acc0005 | B3: 92L O-Rings (Set of 2) | C3: accessories
A4: acc0006 | B4: 126-1 Sealing Rubber, 2.0" | C4: accessories
A5: acc0008 | B5: Easy Care Cuff 1 Hose, Adult XL (1), M4556B, Philips | C5: accessories
A6: acc0009 | B6: Easy Care Cuff 1 Hose, Adult (1), M4555B, Philips | C6: accessories
A7: acc0010 | B7: Adapter Clip, Wide Mouth Clip, 14pcs/pack | C7: accessories
A8: acc0011 | B8: Flow Sensor, FHKSC, Digmesa | C8: accessories
A9: acc0019 | B9: Suction Pipe, 200mm | C9: accessories
A10: acc0020 | B10: Repair Kit Flowmeter PG 858x/9x | C10: accessories
A11: acc0021 | B11: Fitting Kit Flowmeter | C11: accessories
A12: acc0022 | B12: Instrument Multipexer, 6 Positions (main pcb), Planmeca-Finland | C12: accessories
A13: acc0023 | B13: LM Propower Scaler Electronics, Planmeca-Finland | C13: accessories
... A2282: tls1884 | B2282: Addressable Water Sense Cable, 15m, LSZH, FG-EC15, TTK | C2282: tools

Sheet Legal Card Fields
A1: Return
A3: Sr.no. | B3: Field
A4: 1 | B4: Initiated By - Driven
A5: 2 | B5: Initiated By - Landlord
A6: 3 | B6: Initiated By - Tenant
A7: 4 | B7: Property Executive | C7: Will be on the request itself
A8: 5 | B8: Tenant
A9: 6 | B9: Case type
A10: 7 | B10: Type- Reason
A11: 8 | B11: Status
A12: 9 | B12: Alert
A13: 10 | B13: Daily rent
A14: 11 | B14: Property Name
A15: 12 | B15: Unit
A16: 13 | B16: Book
A17: 14 | B17: Start date
A18: 15 | B18: Unpaid charges
A19: 16 | B19: Case number
A20: 17 | B20: Annual Rent
A21: 18 | B21: Calculation Date & Attachement | C21: Manual Calculation attachment. need system to calculate the balance "Add to required customizations list"
A22: 19 | B22: Initial legal call status | C22: legal team contact the tenant
A23: 20 | B23: Police Case
A24: 21 | B24: Nottary Dispatch Date
A25: 22 | B25: Nottary Delivery Date
A26: 23 | B26: Nottary Failed Date
A27: 24 | B27: Nottary End Date
A28: 25 | B28: Nottary News Paper Adv Date
A29: 26 | B29: Nottary News Paper Adv End Date
A30: 27 | B30: Case File Date
A31: 28 | B31: Case Number
A32: 29 | B32: Hearing Date 1
A33: 30 | B33: Hearing Date 2
A34: 31 | B34: Hearing Date 3
... A40: 37 | B40: Execution Number
A41: 38 | B41: Notice for Execution Date | C41: Sharjah and Ajman
A42: 39 | B42: Notice for Execution Status | C42: Sharjah and Ajman
A43: 40 | B43: Investigation Request | C43: Sharjah and Ajman
A44: 41 | B44: Status of Investigation Request | C44: Sharjah and Ajman
A45: 42 | B45: Date of Travel Ban Order
A46: 43 | B46: Date of Travel Ban Execution
A47: 44 | B47: Date of Arrest Warrant
A48: 45 | B48: Date of Actual Arrest
A49: 46 | B49: Date Attach of assets order
A50: 47 | B50: Actual Asset Attach Date
A51: 48 | B51: Travel Ban Execution Number | C51: not required
A52: 49 | B52: Date of Travel Ban | C52: not required
A53: 50 | B53: Eviction Date
A54: 51 | B54: Eviction Postpond Date
A55: 52 | B55: Date of furniture removal approval
A56: 53 | B56: Clearance Approval | C56: Sharjah and Ajman
A57: 54 | B57: Completed | C57: in case of all steps are done but keep case open
A58: 55 | B58: Key Handover Date (To Property Executive)
A59: 56 | B59: Travel Ban Release Date
A60: 57 | B60: Instalment request date (By Tenant)
A61: 58 | B61: Instalment schedule

Sheet Legal- case type & reasons
A1: Return
A3: Standard Types
A4: Case type | B4: Reasons
A5: Bounced Cheques Case- Eviction | B5: Closed account
B6: Customer deceased
B7: Frozen or blocked account
B8: Incorrect cheque details, does not match MICR
B9: Insufficient funds
B10: Items exceed dirham limit or arrangement
B11: Signatory not authorized, or 2nd signature required
B12: Signature irregular
B13: Stale dated cheque or invalid or missing date
B14: Other Reasons
A16: Bounced Cheques Case - Apply for Money | B16: Closed account
B17: Customer deceased
B18: Frozen or blocked account
B19: Incorrect cheque details, does not match MICR
B20: Insufficient funds
B21: Items exceed dirham limit or arrangement
B22: Signatory not authorized, or 2nd signature required
B23: Stale dated cheque or invalid or missing date
B24: Other Reasons
A26: Bounced Cheques Case - Police Report | B26: Signature irregular
A31: Renewal Pending Case- Eviction | B31: Delay in Renewal Process
B32: Dispute in Renewal Notice Rent
A35: Renewal Pending Case - Apply for Money | B35: Delay in Renewal Process
B36: Dispute in Renewal Notice Rent
A39: Tenant Violation Case - Eviction | B39: Illegal activities
B40: Subletting
B41: Nuisance to other tenants
B42: Pets related issues
B43: Bachelors Occupancy
B44: Family Sharing Occupancy
B45: Other Tenant Violations
A47: Outstanding Amount Case - Vacant Mnt Charges | B47: As per Driven Maintenance Report
B48: As per Dubai Muncipality Report
B49: Tenant Filed Case For Security Deposit Refund
A51: Outstanding Amount Case - Utility Charges | B51: Chiller Charges Outstanding
B52: Gas Charges Outstanding
B53: Water Charges Outstanding
B54: Electricity Charges Outstanding
B55: Skip Removal Charges Oustanding
B56: Other Utility Charges Outstanding
A58: Asset damages - Apply for Money | B58: Building Asset damage
B59: Stolen equipments/fittings
B60: Car Accidents in Parking Slot
A62: Asset damages - Eviction | B62: Building Asset damage
B63: Stolen equipments/fittings
B64: Car Accidents in Parking Slot

Sheet Legal Status & Alerts
A1: Return
A2: Standard Values
A3: Sr.no. | B3: Status | C3: Alert | D3: Event | E3: Accept Payment? Yes/No | F3: Automatic Charge Required? | G3: Charge Code | H3: Amount
A4: 1 | B4: In Negotiation | C4: negotiation started
C5: negotiation finished | D5: Negotiation failed
D6: Negotiation succeded
A7: 2 | B7: Handed over to Legal | C7: Handed over to Legal
A8: 3 | B8: Legal Notice | C8: Legal notice served | D8: Tenat replied
D9: Tenant didn't reply
A10: 4 | B10: Lawyer Appointed | C10: Lawyer Appointed
A11: 5 | B11: Case Filed | C11: Case Filed | D11: Case Initiated
A12: 6 | B12: Hearing | C12: Hearing 1
C13: Hearing 2
C14: Hearing 3
C15: Hearing 4
A16: 7 | B16: Judgement Delivered | C16: Judgement Delivered | D16: Verdict in our favor
D17: Verdict not in our favor
A18: 8 | B18: Judgement Execution | C18: Judgement Execution
A19: 9 | B19: Eviction | C19: Eviction started
C20: Eviction Completed
A21: 10 | B21: Funds Received | C21: Full payment received
C22: Partial payment received
A23: 11 | B23: On Hold | C23: On Hold
A24: 12 | B24: Resolved by Legal Team | C24: Case Settled outside court
A25: 12 | B25: Mediaton by RDC | C25: Mediaton by RDC | D25: Mediation Succeded
D26: Mediation Failed
A27: 13 | B27: closed | C27: case closed | D27: Full payment

Sheet Case Requirements
A1: Return
A2: Case Type | B2: Bounced Cheques Case- Eviction | C2: Bounced Cheques Case - Apply for Money | D2: Renewal Pending Case- Eviction | E2: Renewal Pending Case - Apply for Money | F2: Tenant Violation Case - Eviction | G2: Outstanding Amount Case - Vacant Mnt Charges | H2: Outstanding Amount Case - Utility Charges | I2: Asset damages - Apply for Money | J2: Asset damages - Eviction
A3: Documents/Information Required to Open Legal Case | B3: Driven Tenanacy Contract | C3: Driven Tenanacy Contract | D3: Driven Tenanacy Contract | E3: Driven Tenanacy Contract | F3: Driven Tenanacy Contract | G3: Driven Tenanacy Contract | H3: Driven Tenanacy Contract | I3: Driven Tenanacy Contract | J3: Driven Tenanacy Contract
B4: Ejari Contract | C4: Ejari Contract | D4: Ejari Contract | E4: Ejari Contract | F4: Ejari Contract | G4: Ejari Contract | H4: Ejari Contract | I4: Ejari Contract | J4: Ejari Contract
B5: Tenant Emirates ID | C5: Tenant Emirates ID | D5: Tenant Emirates ID | E5: Tenant Emirates ID | F5: Tenant Emirates ID | G5: Tenant Emirates ID | H5: Tenant Emirates ID | I5: Tenant Emirates ID | J5: Tenant Emirates ID
B6: Cheque Memo | C6: Cheque Memo | D6: Renewal Notice | E6: Renewal Notice | F6: Violation Description | G6: Maintenance Inspection Report | H6: Utility Invoice | I6: Police Incident Report | J6: Police Incident Report
B7: Bank Letter | C7: Bank Letter | D7: RERA Index Caluclation | E7: RERA Index Caluclation | F7: Police Report | G7: Trade Licence | H7: Utility Account Statement | I7: Quotation for Rectification | J7: Quotation for Rectification
B8: Rental Caluclation Sheet | C8: Rental Caluclation Sheet | D8: Rental Caluclation Sheet | E8: Rental Caluclation Sheet | F8: Dubai Muncipality Report | G8: Cheque Signatory EID | H8: Trade Licence | I8: Trade Licence | J8: Trade Licence
B9: Third Party Declaration | C9: Third Party Declaration | D9: Trade Licence | E9: Trade Licence | F9: Trade Licence | G9: Trade Lisence Manager EID | H9: Cheque Signatory EID | I9: Cheque Signatory EID | J9: Cheque Signatory EID
B10: Third Party Emirates ID | C10: Third Party Emirates ID | D10: Trade Lisence Manager EID | E10: Trade Lisence Manager EID | F10: Trade Lisence Manager EID | G10: Trade Lisence Partners EID(Sole Est) | H10: Trade Lisence Manager EID | I10: Trade Lisence Manager EID | J10: Trade Lisence Manager EID
B11: Trade Licence | C11: Trade Licence | D11: Trade Lisence Partners EID(Sole Est) | E11: Trade Lisence Partners EID(Sole Est) | F11: Trade Lisence Partners EID(Sole Est) | H11: Trade Lisence Partners EID(Sole Est) | I11: Trade Lisence Partners EID(Sole Est) | J11: Trade Lisence Partners EID(Sole Est)
B12: Signatory EID | C12: Signatory EID | D12: Cheque Signatory EID | E12: Cheque Signatory EID | F12: Cheque Signatory EID
B13: Trade Lisence Manager EID | C13: Trade Lisence Manager EID
B14: Trade Lisence Partners EID(Sole Est) | C14: Trade Lisence Partners EID(Sole Est)
B15: Email ID & Phone for Third Party | C15: Email ID & Phone for Third Party

Sheet  legal Approval WF
A1: Return
A3: Sample Workflows
A5: Category | C5: Current Step | D5: Step Type | E5: Role | F5: Next Step
A6: Renewal Pending Case- Eviction Renewal Pending Case - Apply for Money Tenant Violation Case - Eviction Asset damages - Apply for Money Asset damages - Eviction | C6: Legal Request Created | D6: Start | E6: Property Administrator | F6: Team Leader Approval
C8: Team Leader Approval | D8: Approve | E8: Property Team Leader/Property Manager(Shj&AJM) | F8: Legal Department Action
D9: Reject | F9: Close Request
C10: Legal Department Review | D10: Approve | E10: Legal Senior Executive/Legal Manager | F10: Legal Team Approval | G10: directly to Legal executive in SHJ & AJM
D11: Reject | F11: Close Request
C12: Legal Department Action | D12: Complete | E12: Legal Executive | F12: Create legal card and close request.
D13: Reject | F13: Close Request
A16: Category | C16: Current Step | D16: Step Type | E16: Role | F16: Next Step
A17: Bounced Cheques Case- Eviction Bounced Cheques Case - Apply for Money Bounced Cheque Case - Police Report Outstanding Amount Case - Vacant Mnt Charges Outstanding Amount Case - Utility Charges | C17: Legal Request Created | D17: Start | E17: Debt Collector | F17: Team Leader Approval
C19: Team Leader Approval | D19: Approve | E19: Property Team Leader/Property Manager(Shj&AJM) | F19: Legal Department Action
D20: Reject | F20: Close Request
C21: Legal Department Review | D21: Approve | E21: Legal Senior Executive/Legal Manager | F21: Legal Team Approval | G21: directly to Legal executive in SHJ & AJM
D22: Reject | F22: Close Request
C23: Legal Department Action | D23: Complete | E23: Legal Executive | F23: Create legal card and close request.
D24: Reject | F24: Close Request
A28: one more workflow for accepting partial payment for running case same steps to be followed
A30: one more workflow to close legal case will follow the same steps
A34: one more workflow to lift travel ban only, case will continue in RDC | D34: lease executive

Sheet Legal Notice Formats
A1: Return
A4: Event: Legal Card Created
A5: Outstanding Balance Notice (Dubai) | D5: Non-Renewal (Dubai) | F5: Tenant Violations | H5: Outstanding amount | J5: Maintenance damages
A6: Tenant Name: XXXX Unit No: XXXX Building: XXXX Subject: Cheque Bounce Action Notice. Dear Valued Tenant, Greetings! Pursuant to the Lease Agreement dated on xxxx, please be informed that you are in serious default of your contractual obligations as you have failed to settle the outstanding rent as per the mutually agreed provisions of the Lease Agreement. Therefore, in light of the above and as a measure of good faith, we will provide you with seven (7) days commencing from the date of receipt of this legal notice to remit the full outstanding amount of AED ............../- UAE Dirhams Only and Cheque bounce penalty amount of AED ................/- UAE Dirhams Only. In the event you fail to pay the outstanding amount then your file will be handled by our Legal Team. Upon initiating the legal proceedings (civil and criminal –including travel ban), you will then be required to pay the total outstanding amounts along with the court fees and all related legal costs. Consider this as final opportunity to settle the matter amicably, thereafter you will be responsible to bear all legal costs and damages. This notice is issued without prejudice to any of our rights, all of which are hereby reserved. If you have already paid all the above outstanding amount, kindly request you to ignore this email. Thanking you for your immediate response and action. Regards, XXXXXXXXX | B6: اللغة العربية: | D6: Tenant Name: XXXX Unit No: XXXX Building: XXXX Subject: Action notice for pending renewal. Dear Valued Tenant, Greetings! We, Driven Real Estate would like to informed you that the lease period of the above-mentioned premise was expired on XXXX So, due to delay in the above renewal, we kindly inform you that if you are not completing the renewal process today XXXX with AED XXXX Late Renewal fees after receiving this notice, we will be forced to initiate legal action against your leased unit. Note: · If any existing legal case in the rental dispute centre or having any outstanding dues in the previous contract, the tenant shall not be eligible for the next year renewal. · If the RDC has filed, the charges will applicable as per your rent specified by the RDC and additional AED XXXX as legal processing charge. · For each notary attested letter AED XXXX is applicable and additional AED XXXX as legal processing charge. If you have already issued the renewals cheques, kindly request you to ignore this email. Thanking you for your immediate response and action. Regards, XXXXXXXXX
A10: Outstanding Balance Notice (Shj/AJM) | D10: Non-Renewal (Shj/Ajm) | F10: Tenant Violations | H10: Outstanding amount | J10: Maintenance damages
A14: Event: Case Filed
A16: Legal Case Intimation to Tenant (Cheque Bounce) - Sharjah/Ajman | D16: Legal Case Intimation to Tenant (Renewal Pending) - Sharjah/Ajman | F16: Tenant Violations | H16: Outstanding amount | J16: Maintenance damages
A17: Tenant Name: XXXX Unit No: XXXX Building: XXXX Subject: Cheque Bounce Action Notice. Dear Valued Tenant, Greetings! Pursuant to the Lease Agreement dated on xxxx, please be informed that you are in serious default of your contractual obligations as you have failed to settle the outstanding rent as per the mutually agreed provisions of the Lease Agreement. Therefore, in light of the above and as a measure of good faith, we will provide you with seven (7) days commencing from the date of receipt of this legal notice to remit the full outstanding amount of AED ............../- UAE Dirhams Only and Cheque bounce penalty amount of AED ................/- UAE Dirhams Only. In the event you fail to pay the outstanding amount then your file will be handled by our Legal Team. Upon initiating the legal proceedings, you will then be required to pay the total outstanding amounts along with the court fees and all related legal costs. Consider this as final opportunity to settle the matter amicably, thereafter you will be responsible to bear all legal costs and damages. This notice is issued without prejudice to any of our rights, all of which are hereby reserved. If you have already paid all the above outstanding amount, kindly request you to ignore this email. Thanking you for your immediate response and action. Regards, XXXXXXXXX | B17: اسم المستأجر رقم الوحدة : XXX بناية : XXX الموضوع: إشعار إتخاذ إجراء بخصوص الشيكات المرتده عزيزى المستأجر بعد التحيه ،،، وفقًا لعقد الإيجار المؤرخ بتاريخ xxxx، يرجى العلم بأنك تتخلف عن الوفاء بالتزاماتك التعاقدية حيث انك لم تقم بتسوية الإيجار المستحق وفقًا للأحكام المتفق عليها بشكل متبادل في عقد الإيجار لذلك، في ضوء ما ورد اعلاه وكإجراء لحسن النية، سنمنحك سبعة (7) أيام تبدأ من تاريخ استلام هذا الإشعار القانوني لتحويل كامل المبلغ المستحق وقدره ....... ......./- درهم إماراتي ومبلغ غرامة الشيكات المرتجعة ................/- درهم. في حالة عدم دفع المبلغ المستحق، سيتم التعامل مع ملفك من قبل القسم القانوني. لبدء الإجراءات القانونية ، سيُطلب منك بعد ذلك دفع إجمالي المبالغ المستحقة بالإضافة إلى رسوم المحكمة وجميع التكاليف القانونية ذات الصلة. تعتبر هذه فرصة أخيرة لتسوية الأمر وديًا، وبعد ذلك ستكون مسؤولاً عن تحمل جميع التكاليف والأضرار القانونية. تم إصدار هذا الإشعار دون المساس بأي من حقوقنا، وجميعها محفوظة. إذا كنت قد دفعت بالفعل كامل المبلغ المستحق أعلاه، فيرجى تجاهل هذه الرسالة. نشكرك على استجابتك وردك الفورى علينا تحياتى ، XXXXXXXXX | D17: Tenant Name: XXXX Unit No: XXXX Building: XXXX Subject: Action notice for pending renewal. Dear Valued Tenant, Greetings! We, Driven Real Estate would like to informed you that the lease period of the above-mentioned premise was expired on XXXX So, due to delay in the above renewal, we kindly inform you that if you are not completing the renewal process today XXXX after receiving this notice, we will be forced to initiate legal action. Note: · If any existing legal case in the rental dispute Centre or having any outstanding dues in the previous contract, the tenant shall not be eligible for the next year renewal. · If the municipality case has been filed, the charges will applicable as per your rent specified by the municipality and additional AED XXXX as legal processing charge. If you have already issued the renewals cheques, kindly request you to ignore this email. Thanking you for your immediate response and action. Regards, XXXXXXXXX | E17: اسم المستأجر رقم الوحدة : XXX بناية : XXX الموضوع: إشعار إتخاذ إجراء بخصوص عدم التجديد عزيزى المستأجر بعد التحيه ،،، نود نحن شركة اس بي كيه للعقارات إبلاغكم بأن فترة إيجار الوحدة المذكورة أعلاه قد انتهت بتاريخ XXXX لذا، نظرًا للتأخير في التجديد أعلاه، يرجى إبلاغك أنه إذا لم تقم بإكمال عملية التجديد اليوم XXXX بعد تلقي هذا الإشعار، فسنضطر إلى اتخاذ الإجراء القانوني اللازم. ملحوظة : - في حالة وجود دعوى قانونية قائمة في مركز فض المنازعات الإيجارية أو وجود أي مستحقات مستحقة في العقد السابق، فلن يكون المستأجر مؤهلاً للتجديد للعام التالي. - إذا تم رفع قضية لدى البلدية، فسيتم تطبيق الرسوم وفقًا لإيجارك المحدد من قبل البلدية بالإضافة إلى XXXX درهم إماراتي كرسوم معالجة قانونية. إذا كنت قد أصدرت بالفعل شيكات التجديد، فيرجى تجاهل هذة الرسالة. نشكرك على استجابتك وردك الفورى علينا تحياتى ، XXXXXXXXX
A20: Case Opened Intimation to Tenant (Cheque Bounce) - Sharjah/Ajman | D20: Case Opened Intimation to Tenant (Renewal Pending) - Sharjah/Ajman
A21: To, Tenant Details Sub: Municipality Case for Outstanding This is to inform you that, a Municipality case (case no.) has been initiated against your non-payment of outstanding rent (cheque amount and date) in defiance of the repeated reminder to clear the same. Henceforth, we request you to clear all your outstanding amount and legal charges incurred by the company in a total amount of (AED….) at the earliest to eschew eviction. | B21: اللغة العربية:اخطار القضية المفتوحة للمستأجر (عن شيكات مرتجعة) الى ، بيانات المستأجر الموضوع : قضية بلدية بخصوص المستحقات الايجارية هذا لإعلامك بأنه قد تم رفع دعوى بالبلدية (رقم القضية) بسبب عدم دفع الإيجار المستحق (مبلغ الشيك والتاريخ) وذلك بعد التذكير المتكرر لتسوية المستحقات. من الآن فصاعدا، نطلب منك تسوية جميع المبالغ المستحقة والرسوم القانونية التي تكبدتها الشركة بإجمالى مبلغ وقدره (....... درهم إماراتي) في أقرب وقت ممكن لتجنب الإخلاء. | D21: To, Tenant Details Sub : Municipality Case for Outstanding This is to inform you that, a Municipality case (case no.) has been initiated against your failure of rental agreement renewal which has expired on (contract expiry date) in defiance to the repeated reminder of the same. Henceforth, we request you to renew the rental agreement and pay the legal charges of (AED…..) incurred by the company at the earliest to eschew eviction. | E21: اخطار القضية المفتوحة من قسم الشئون القانونية – الى المدير العقارى (عن شيكات مرتجعة) الى ، المدير العقارى الموضوع : قضية بلدية بخصوص المستحقات الايجارية هذا لإعلامك بالإشارة إلى عقد الإيجار (بيانات المستأجر)، قد تم رفع قضية (رقم القضية) لدى البلدية للمطالبه بالمبلغ المستحق (تفاصيل الشيك) و تم دفع رسوم قانونية عليه بقيمة (درهم....) من قبل الشركة والتي يجب استردادها من المستأجر
A23: Case Opened Intimation from Legal Dept. to Property Admin. (Cheque Bounce) - Sharjah/Ajman | D23: Case Opened Intimation from Legal Dept. to Property Admin. (Renewal Pending) - Sharjah/Ajman
A24: To, Property Administrator Sub : Municipality Case for Outstanding This is to inform you in reference to the rental agreement (Tenant details) a case (case no.) has been initiated with the Municipality for the outstanding amount (cheque details) to which a legal charge of (AED ….) has been incurred by the company which has to be recovered from the tenant. | B24: اخطار القضية المفتوحة من قسم الشئون القانونية – الى المدير العقارى (عن شيكات مرتجعة) الى ، المدير العقارى الموضوع : قضية بلدية بخصوص المستحقات الايجارية هذا لإعلامك بالإشارة إلى عقد الإيجار (بيانات المستأجر)، قد تم رفع قضية (رقم القضية) لدى البلدية للمطالبه بالمبلغ المستحق (تفاصيل الشيك) و تم دفع رسوم قانونية عليه بقيمة (درهم....) من قبل الشركة والتي يجب استردادها من المستأجر | D24: To, Property Administrator Sub : Municipality Case for Renewal Pending This is to inform you in reference to the rental agreement (Tenant details) a case (case no.) has been initiated with the Municipality for renewal pending from (contract expiry date) to which a legal charge of (AED ….) has been incurred by the company which has to be recovered from the tenant. | E24: اخطار القضية المفتوحة من قسم الشئون القانونية – الى المدير العقارى (بخصوص عدم التجديد) الى ، المدير العقارى الموضوع : قضية بلدية بخصوص عدم التجديد هذا لإعلامك بالإشارة إلى عقد الإيجار (تفاصيل المستأجر) فقد تم رفع قضية (رقم القضية) لدى البلدية لعدم التجديد من (تاريخ انتهاء العقد) و تم دفع رسوم قانونية لها بقيمة (درهم….) والتي يجب استردادها من المستأجر
A27: Case Cancellation Intimation from Legal Dept. to Property Admin. (Cheque Bounce) - Sharjah/Ajman | D27: Case Cancellation Intimation from Legal Dept. to Property Admin. (Renewal Pending) - Sharjah/Ajman
A28: To, Property Administrator This is in reference to the case (case no.) initiated against tenant (Tenant details) for cheque bounce (cheque details). We inform you that the case has been cancelled as the tenant has cleared all his outstanding debts and legal charges of (AED….) towards the company. | B28: إشعار بإلغاء القضية من قسم الشئون القانونية إلى المدير العقارى. (شيكات مرتجعة) الى ، المدير العقارى هذا بالإشارة إلى القضية (رقم القضية) المرفوعة ضد المستأجر (تفاصيل المستأجر) بشأن الشيك المرتجع (تفاصيل الشيك). نفيدكم بإلغاء القضية حيث قام المستأجر بتسوية جميع ديونه المستحقة والرسوم القانونية بإجمالى مبلغ (درهم….). | D28: To, Property Administrator This is in reference to the case (case no.) initiated against tenant (Tenant details) for renewal pending, for the contract which has expired on (contract expiry date). We inform you that the case has been cancelled as the tenant has renewed the contract and paid legal charges of (AED….) towards the company. | E28: إشعار بإلغاء القضية من قسم الشئون القانونية إلى المدير العقارى. (شيكات مرتجعة) الى ، المدير العقارى هذا بالإشارة إلى القضية (القضية رقم) المرفوعة ضد المستأجر (تفاصيل المستأجر) بسبب عدم التجديد للعقد الذي انتهى في (تاريخ انتهاء العقد). نفيدكم بإلغاء القضية حيث قام المستأجر بتجديد العقد ودفع الرسوم القانونية البالغة (درهم….).

Sheet Legal Notifications
A1: Return
A3: Number | B3: Type | C3: Event | D3: Receiver | E3: Comment
A4: 1 | B4: Notice to Tenant | C4: Legal Card Created | D4: Tenant/Property Admin/Collector
A5: 2 | B5: Notice to Tenant | C5: Case Filed | D5: Tenant/Property Admin/Collector
A6: 3 | B6: Notice to Admin | C6: Eviction Completed | D6: Property Admin | E6: "To Terminate contract in system and vacate unit"
A7: 4 | B7: Notice to Admin | C7: Completed | D7: Property Admin

Sheet RFI_Changes_analysis
A1: Driven Real Estate Yardi Implementation - Request For Information Tracker
A2: Request for Information
A3: Sr.No. | B3: Yardi Module | C3: BPR Reference | D3: Requirements (What we want?) | E3: Department | F3: Priority | G3: Project Team Member | H3: Shared Date | I3: Target Date | J3: Received Status | K3: Received Date | L3: Remarks | M3: Changes after Sign-off | N3: Closure remarks | O3: Delayed Days | P3: Dependency | Q3: Configured in Live | R3: Driven Feedback
A4: 1 | B4: Master | C4: MD 1.06 | D4: Porfolio details | E4: Finance & Renewal | F4: High | G4: Anas | H4: 45147 | I4: 45149 | J4: Yes | K4: 45159
A5: =A4+1 -> 2 | B5: Master | C5: MD 1.07 | D5: Additional Fields on the Legal Entity | E5: Finance & Renewal | F5: High | G5: Anas | H5: 45147 | I5: 45149 | J5: Yes | K5: 45159
A6: =A5+1 -> 3 | B6: Master | C6: MD 1.08 | D6: Legal Entity - Contact Roles | E6: Finance & Renewal | F6: High | G6: Anas | H6: 45147 | I6: 45149 | J6: Yes | K6: 45159
A7: =A6+1 -> 4 | B7: Master | C7: MD 1.09 | D7: Legal Entity - Attachment types | E7: Finance & Renewal | F7: Medium | G7: Anas | H7: 45147 | I7: 45149 | J7: Yes | K7: 45159
A8: =A7+1 -> 5 | B8: Master | C8: MD 1.11 | D8: Additional Fields on the Property Level | E8: Finance & Renewal | F8: High | G8: Anas | H8: 45147 | I8: 45149 | J8: Yes | K8: 45159 | L8: Update BD process related information for PMLA
A9: =A8+1 -> 6 | B9: Master | C9: MD 1.13 | D9: Property Attributes | E9: Finance & Renewal | F9: High | G9: Anas | H9: 45147 | I9: 45149 | J9: Yes | K9: 45159 | L9: Shoeb to check & confirm if FM reports available by Attributes.
A10: =A9+1 -> 7 | B10: Master | C10: MD 1.14 | D10: Property - Contact Roles | E10: Finance & Renewal | F10: High | G10: Anas | H10: 45147 | I10: 45149 | J10: Yes | K10: 45159
A11: =A10+1 -> 8 | B11: Master | C11: MD 1.15 | D11: Property - Attachment types | E11: Finance & Renewal | F11: Medium | G11: Anas | H11: 45147 | I11: 45149 | J11: Yes | K11: 45159
A12: =A11+1 -> 9 | B12: Master | C12: MD 1.23 | D12: Unit Attributes | E12: Finance & Renewal | F12: Medium | G12: Anas | H12: 45147 | I12: 45149 | J12: Yes | K12: 45159
A13: =A12+1 -> 10 | B13: Master | C13: MD 1.23 | D13: Amenities - Property and Unit | E13: Finance & Renewal | F13: High | G13: Anas | H13: 45147 | I13: 45149 | J13: Yes | K13: 45159
A14: =A13+1 -> 11 | B14: Master | C14: MD 1.23 | D14: Unit Types | E14: Finance & Renewal | F14: High | G14: Anas | H14: 45147 | I14: 45149 | J14: Yes | K14: 45159
A15: =A14+1 -> 12 | B15: Master | C15: MD 1.24 | D15: Unit - Attachment Types | E15: Finance & Renewal | F15: Medium | G15: Anas | H15: 45147 | I15: 45149 | J15: Yes | K15: 45159
A16: =A15+1 -> 13 | B16: Residential Leasing | C16: LA001.5 | D16: Customer Types | E16: Leasing Team | F16: Medium | G16: Anas | H16: 45152 | I16: 45155 | J16: Yes | K16: 45159
A17: =A16+1 -> 14 | B17: Residential Leasing | C17: LA001.5 | D17: Customer Additional Information | E17: Leasing Team | F17: Medium | G17: Anas | H17: 45152 | I17: 45155 | J17: Yes | K17: 45159
A18: =A17+1 -> 15 | B18: Residential Leasing | C18: LA001.6 | D18: Customer Level Attachments | E18: Leasing Team | F18: Medium | G18: Anas | H18: 45152 | I18: 45155 | J18: Yes | K18: 45159
A19: =A18+1 -> 16 | B19: Residential Leasing | C19: LA001.6 | D19: Guest/Prospect Level Attachments | E19: Leasing Team | F19: Medium | G19: Anas | H19: 45152 | I19: 45155 | J19: Yes | K19: 45159
A20: =A19+1 -> 17 | B20: Residential Leasing | C20: LA001.6 | D20: Tenant Level Attachments | E20: Leasing Team | F20: Medium | G20: Anas | H20: 45152 | I20: 45155 | J20: Yes | K20: 45159
A21: =A20+1 -> 18 | B21: Residential Leasing | C21: LA001.7 | D21: Customer - Contact Roles | E21: Leasing Team | F21: Medium | G21: Anas | H21: 45152 | I21: 45155 | J21: Yes | K21: 45159
A22: =A21+1 -> 19 | B22: Residential Leasing | D22: Guest Template | E22: Leasing Team | F22: Medium | G22: Anas | H22: 45152 | I22: 45155 | J22: Yes | K22: 45181 | L22: SBK team to internally finalise for guest tempate bifurcation - Shop, Warehouse, Showroom. SBK : Finalised, kindly review (12.09.23) Yardi-21Sept2023: Guest template is finalised and for commercial there would be multiple templates as for each template there would be difference charge code - Shop, warehouse etc.
A23: =A22+1 -> 20 | B23: Residential Leasing | C23: LA001.10 | D23: Applicant/Tenant Charge Fees Matrix | E23: Leasing Team | F23: Medium | G23: Anas | H23: 45152 | I23: 45155 | J23: No | L23: Finalised, kindly review (12.09.23)
A24: =A23+1 -> 21 | B24: Residential Leasing | D24: Discounts and concessions given to tenants | E24: Leasing Team | F24: Medium | G24: Anas | H24: 45163 | I24: 45163 | J24: Yes | L24: Rental Discounts are noted, Team to check if any specific discounts are given. 31-Aug-2023 (Yardi): As discussed with team, provided list is complete. SBK will add if any other scenario encountered in future.
A25: =A24+1 -> 22 | B25: Residential Leasing | C25: LA001.20 | D25: Additional Occupant Details | E25: Leasing Team | F25: Medium | G25: Anas | H25: 45152 | I25: 45155 | J25: Yes | K25: 45159
A26: =A25+1 -> 23 | B26: Residential Leasing | D26: Residential - New Lease Approval Workflow | E26: Leasing Team | F26: High | G26: Anas | H26: 45152 | I26: 45155 | J26: Yes | K26: 45161
A27: =A26+1 -> 24 | B27: Residential Leasing | D27: Residential - New Lease Execution Workflow | E27: Leasing Team | F27: High | G27: Anas | H27: 45152 | I27: 45155 | J27: Yes | K27: 45161
A28: =A27+1 -> 25 | B28: Residential Leasing | D28: Residential - Move-In Workflow | E28: Leasing Team | F28: High | G28: Anas | H28: 45152 | I28: 45155 | J28: Yes | K28: 45161
A29: =A28+1 -> 26 | B29: Residential Leasing | C29: LG001.1 | D29: Residential - Renewal Workflow | E29: Leasing Team | F29: High | G29: Anas | H29: 45152 | I29: 45155 | J29: Yes | K29: 45163
A30: =A29+1 -> 27 | B30: Residential Leasing | C30: LG001.16 | D30: Residential - Move-out Workflow | E30: Leasing Team | F30: High | G30: Anas | H30: 45152 | I30: 45155 | J30: Yes | K30: 45163
A31: =A30+1 -> 28 | B31: Residential Leasing | C31: LG001.8 | D31: Tenant Level Attachments - Documents to be submitted by tenants during renewal | E31: Leasing Team | F31: Medium | G31: Anas | H31: 45152 | I31: 45155 | J31: Yes | K31: 45163
A32: =A31+1 -> 29 | B32: Residential Leasing | C32: LG001.9 | D32: Applicant/Tenant Charge Fees Matrix - During renewal | E32: Leasing Team | F32: Medium | G32: Anas | H32: 45152 | I32: 45155 | J32: Yes
A33: =A32+1 -> 30 | B33: Residential Leasing | C33: LG001.18 | D33: Early Termination Charges for tenant | E33: Leasing Team | F33: Medium | G33: Anas | H33: 45152 | I33: 45155 | J33: Yes | K33: 45163
A34: =A33+1 -> 31 | B34: Residential Leasing | C34: LG001.19 | D34: Tenant Move-Out Reasons | E34: Leasing Team | F34: Medium | G34: Anas | H34: 45152 | I34: 45155 | J34: Yes | K34: 45163
A35: =A34+1 -> 32 | B35: Residential Leasing | D35: Tenant Memo Types | E35: Leasing Team | F35: Medium | G35: Anas | H35: 45163 | I35: 45163 | J35: Yes | K35: 45163
A36: =A35+1 -> 33 | B36: Residential Leasing | D36: Tenant Service requests and DOA | E36: Leasing Team | F36: Medium | G36: Anas | J36: Yes | K36: 45181 | L36: (Finalised on 11.09.23) Service request for Waiver & RDC Legal case pending Yardi : 15-Sept-2023 : SR for RDC Legal was only pending and this is handled by Hatem in Legal sessions & workflows.
A37: =A36+1 -> 34 | B37: Accounts Receivable | C37: AR 001 | D37: Chart of Accounts (COA) | E37: Finance | F37: High | G37: Anas | H37: 45154 | I37: 45156 | J37: Partial | K37: 45181 | L37: Finalised, kindly review (12.09.23) Yardi21Sept2023 : This needs to be checked along with Charge codes to verify the completeness.
A38: =A37+1 -> 35 | B38: Accounts Receivable | C38: AR 002 | D38: Charge codes | E38: Finance | F38: High | G38: Anas | H38: 45154 | I38: 45156 | J38: Yes | K38: 45181 | L38: Finalised, kindly review (12.09.23)
A39: =A38+1 -> 36 | B39: Accounts Receivable | C39: AR 003 | D39: Role based details of Finance functions. | E39: Finance | F39: High | G39: Anas | H39: 45154 | I39: 45156 | J39: Yes | K39: 45181
A40: =A39+1 -> 37 | B40: Accounts Receivable | C40: AR 004 | D40: In case of advance receipts-sequence in which charges would be applied. | E40: Finance | F40: Medium | G40: Anas | H40: 45154 | I40: 45156 | J40: Not Req | L40: Any Application of advances to the O/S should be done on Case to case basis.
A41: =A40+1 -> 38 | B41: Accounts Receivable | C41: AR 030 | D41: Provide us the details for which bank charges are charged for bounce cheques. | E41: Finance | F41: Medium | G41: Anas | H41: 45154 | I41: 45156 | J41: Not Req | L41: This is applicable for Sharjah LL but LL banks are not managed by SBK & therefore this is not applicable.
A42: =A41+1 -> 39 | B42: Accounts Receivable | C42: AR 032 | D42: PDC Bank Names | E42: Finance | F42: Medium | G42: Anas | H42: 45156 | I42: 45160 | J42: Yes
A43: =A42+1 -> 40 | B43: Property Management | C43: PM009 | D43: PM Fees Calculation | E43: Finance | F43: High | G43: Anas | H43: 45156 | I43: 45160 | J43: Yes | K43: 45180 | L43: Provided data in DM templates directly.
A44: =A43+1 -> 41 | B44: General Ledger | C44: GL001.2 | D44: SBK to provide the Manual Scenario of Journal Entries. (Salary GL allocation entries). | E44: Finance | F44: High | G44: Anas | H44: 45156 | I44: 45160 | J44: Yes | K44: 45180
A45: =A44+1 -> 42 | B45: General Ledger | C45: GL002.3 | D45: Prepay Mapping | E45: Finance | F45: Medium | G45: Anas | H45: 45156 | I45: 45160 | J45: Yes | K45: 45180
A46: =A45+1 -> 43 | B46: General Ledger | C46: GL007.10 | D46: Segments to be created. | E46: Finance | F46: Medium | G46: Anas | H46: 45156 | I46: 45160 | J46: Yes | K46: 45180
A47: =A46+1 -> 44 | B47: General Ledger | D47: SBK to provide the details for the current petty cash processes & Booking. | E47: Finance | F47: Medium | G47: Anas | H47: 45156 | I47: 45160 | J47: Not Req | L47: Petty Cash process is discussed in AP session and is finalised. Same process to be followed.
A48: =A47+1 -> 45 | B48: General Ledger | C48: GL008.1 | D48: MT940 format for each bank to be shared. | E48: Finance | F48: Medium | G48: Anas | H48: 45156 | I48: 45160 | J48: Yes
A49: =A48+1 -> 46 | B49: General Ledger | C49: GL009.4 | D49: Tax Tran Types - Confirmation pending | E49: Finance | F49: High | G49: Anas | H49: 45156 | I49: 45160 | J49: Yes | K49: 45184
A50: =A49+1 -> 47 | B50: General Ledger | C50: GL addl.1 | D50: Scenario that are not covered in the Session, can be listed as Scenarios in this Sections. | E50: Finance | F50: Medium | G50: Anas | H50: 45156 | I50: 45160 | J50: Yes
A51: =A50+1 -> 48 | B51: General Ledger | C51: GL addl.2 | D51: Intercompany Scenarios to be provided | E51: Finance | F51: High | G51: Anas | H51: 45156 | I51: 45160 | J51: Yes | K51: 45179
A52: =A51+1 -> 49 | B52: General Ledger | C52: GL addl.3 | D52: Month end Checklist | E52: Finance | F52: Medium | G52: Anas | H52: 45156 | I52: 45160 | J52: No | L52: Month end checklist not to be tracked till end of trainings and to be finalised upon completion of trainings.
A53: =A52+1 -> 50 | B53: BD Process | C53: BDP 1.3 | D53: BD Workflows - Approving LL leads (Service request) | E53: BD | F53: High | G53: Anas | H53: 45156 | I53: 45160 | J53: No | L53: Change the Dept. to BD
A54: =A53+1 -> 51 | B54: BD Process | C54: BDP 1.5 | D54: Attachment Types under this process | E54: BD | F54: High | G54: Anas | H54: 45156 | I54: 45160 | J54: No | L54: Change the Dept. to BD
A55: =A54+1 -> 52 | B55: BD Process | C55: BDP 1.6 | D55: BD Workflows - APproving Head leases (Amendment WF) | E55: BD | F55: High | G55: Anas | H55: 45156 | I55: 45160 | J55: No | L55: Change the Dept. to BD
A56: =A55+1 -> 53 | B56: BD Process | C56: BDP 1.7 | D56: Charge codes for head lease | E56: BD | F56: High | G56: Anas | H56: 45156 | I56: 45160 | J56: No | L56: Change the Dept. to BD
A57: =A56+1 -> 54 | B57: BD Process | C57: BDP 1.7 | D57: Lease Type for head lease | E57: BD | F57: High | G57: Anas | H57: 45156 | I57: 45160 | J57: No | L57: Change the Dept. to BD
A58: =A57+1 -> 55 | B58: BD Process | D58: Type of activites to be tracked at headlease proposal | E58: BD | F58: High | G58: Anas | H58: 45156 | I58: 45160 | J58: No | L58: Change the Dept. to BD
A59: =A58+1 -> 56 | B59: BD Process | C59: BDA1.2 | D59: Requirements for lessee accounting - GL accounts, etc. | E59: BD | F59: High | G59: Anas | H59: 45156 | I59: 45160 | J59: No | L59: Change the Dept. to BD
A60: =A59+1 -> 57 | B60: BD Process | C60: BDP 1.9 | D60: Holdover process for Head Lease | E60: BD | F60: High | G60: Anas | H60: 45156 | I60: 45160 | J60: No | L60: Change the Dept. to BD
A61: =A60+1 -> 58 | B61: BD Process | C61: BDA1.5 | D61: Security Deposit process for Head Lease | E61: BD | F61: High | G61: Anas | H61: 45156 | I61: 45160 | J61: No | L61: Change the Dept. to BD
A62: =A61+1 -> 59 | B62: BD Process | C62: BDA1.1 | D62: Head Lease accounting process - Signoff | E62: BD | F62: High | G62: Anas | H62: 45156 | I62: 45160 | J62: No | L62: Change the Dept. to BD
A63: =A62+1 -> 60 | B63: BD Process | C63: BDA1.6 | D63: Finance cost involved for Head leases above 12 months | E63: BD | F63: High | G63: Anas | H63: 45156 | I63: 45160 | J63: No | L63: Change the Dept. to BD
A64: =A63+1 -> 61 | B64: Property Takeover-Handover | C64: 5 | D64: How many days required to complete the takeover process - Complete Process | E64: Finance | F64: High | G64: Anas | H64: 45166 | I64: 45168 | J64: Yes | L64: 7 days from Handover Date
A65: =A64+1 -> 62 | B65: Property Takeover-Handover | C65: 6 | D65: List of documents - Information and Contract related details to be listed. | E65: Finance | F65: High | G65: Anas | H65: 45166 | I65: 45168 | J65: Yes
A66: =A65+1 -> 63 | B66: Property Takeover-Handover | C66: 10 | D66: Property Takeover scenarios with details | E66: Finance | F66: High | G66: Anas | H66: 45166 | I66: 45168 | J66: No
A67: =A66+1 -> 64 | B67: Property Takeover-Handover | C67: 10 | D67: Property Takeover - Tenant Settlement Scenarios | E67: Finance | F67: High | G67: Anas | H67: 45166 | I67: 45168 | J67: No
A68: =A67+1 -> 65 | B68: Property Takeover-Handover | C68: 14 | D68: PM Fees calculation scenarios during takeover - All elements considered (O/s, Receipts etc) | E68: Finance | F68: High | G68: Anas | H68: 45166 | I68: 45168 | J68: No
A69: =A68+1 -> 66 | B69: Property Takeover-Handover | C69: 18 | D69: PMA Agreements- Samples with all scenarios (Revenue based,Collection, fixed) any exceptional scenario. | E69: Finance | F69: High | G69: Anas | H69: 45166 | I69: 45168 | J69: No
A70: =A69+1 -> 67 | B70: Legal | D70: Legal case type and reasons | E70: Legal | F70: High | G70: Anas | H70: 45153 | I70: 45168 | J70: Yes | K70: 45175
A71: =A70+1 -> 68 | B71: Legal | D71: Legal card fields | E71: Legal | F71: High | G71: Anas | H71: 45153 | I71: 45168 | J71: Yes | K71: 45175
A72: =A71+1 -> 69 | B72: Legal | D72: Legal status and alert | E72: Legal | F72: High | G72: Anas | H72: 45153 | I72: 45168 | J72: Yes | K72: 45175
A73: =A72+1 -> 70 | B73: Legal | D73: List of Requirements for legal case | E73: Legal | F73: Medium | G73: Anas | H73: 45153 | I73: 45168 | J73: Yes | K73: 45175
A74: =A73+1 -> 71 | B74: Legal | D74: Legal approval WF | E74: Legal | F74: Medium | G74: Anas | H74: 45153 | I74: 45168 | J74: Yes | K74: 45175
A75: =A74+1 -> 72 | B75: Legal | D75: Legal Notice Formats | E75: Legal | F75: Medium | G75: Anas | H75: 45153 | I75: 45168 | J75: Partial
A76: =A75+1 -> 73 | B76: Vendor Café | C76: P2P3 | D76: Vendor Markets | E76: Procurement | F76: High | H76: 45147 | I76: 45149 | J76: Yes | K76: 45162
A77: =A76+1 -> 74 | B77: Vendor Café | C77: P2P4, P2P5 | D77: Vendor Categories and Insurance Types | E77: Procurement | F77: High | H77: 45147 | I77: 45149 | J77: Yes | K77: 45162
A78: =A77+1 -> 75 | B78: Vendor Café | C78: P2P6 | D78: Workflow for Vendors | E78: Procurement | F78: High | H78: 45147 | I78: 45149 | J78: Yes | K78: 45162
A79: =A78+1 -> 76 | B79: Vendor Café | C79: P2P7 | D79: Mandatory documents for Vendor Registration | E79: Procurement | F79: High | H79: 45147 | I79: 45149 | J79: Yes | K79: 45162
A80: =A79+1 -> 77 | B80: Vendor Café | C80: P2P14 | D80: User Defined Field | E80: Procurement | F80: High | H80: 45147 | I80: 45149 | J80: Yes | K80: 45162
A81: =A80+1 -> 78 | B81: Vendor Café | C81: P2P15 | D81: Vendor Agreement | E81: Procurement | F81: High | H81: 45147 | I81: 45149 | J81: No
A82: =A81+1 -> 79 | B82: Vendor Café | C82: P2P16 | D82: Vendor Cafe configurations | E82: Procurement | F82: High | H82: 45147 | I82: 45149 | J82: Yes | K82: 45162
A83: =A82+1 -> 80 | B83: Vendor Café | C83: P2P17 | D83: VC Email Templates | E83: Procurement | F83: High | H83: 45147 | I83: 45149 | J83: Yes | K83: 45162
A84: =A83+1 -> 81 | B84: Vendor Café | C84: P2P19 | D84: Support numbers/email | E84: Procurement | F84: High | H84: 45147 | I84: 45149 | J84: Yes | K84: 45162
A85: =A84+1 -> 82 | B85: Vendor Café | D85: EFT Format | E85: Procurement | F85: High | H85: 45147 | I85: 45149 | J85: Yes
A86: =A85+1 -> 83 | B86: P2P | C86: AP1.1 | D86: Person creating PO | E86: Procurement | F86: High | H86: 45147 | I86: 45152 | J86: Yes | K86: 45162 | M86: Y
A87: =A86+1 -> 84 | B87: P2P | C87: AP1.1 | D87: Person creating Invoice | E87: Procurement | F87: High | H87: 45147 | I87: 45152 | J87: Yes | K87: 45162
A88: =A87+1 -> 85 | B88: P2P | C88: AP1.3 | D88: Provide a list of Expense types | E88: Procurement | F88: Critical | H88: 45147 | I88: 45152 | J88: Yes | K88: 45162
A89: =A88+1 -> 86 | B89: P2P | C89: AP1.4 | D89: PR and PO Approval Workflow | E89: Procurement | F89: Critical | H89: 45147 | I89: 45152 | J89: Yes | K89: 45162 | M89: Y
A90: =A89+1 -> 87 | B90: P2P | C90: AP1.5 | D90: PO attachment types | E90: Procurement | F90: High | H90: 45147 | I90: 45152 | J90: Yes | K90: 45162
A91: =A90+1 -> 88 | B91: P2P | C91: AP1.6 | D91: Invoice approval DOA | E91: Procurement | F91: High | H91: 45147 | I91: 45152 | J91: Yes | K91: 45162
A92: =A91+1 -> 89 | B92: P2P | C92: AP1.7 | D92: Invoice Attachment types | E92: Procurement | F92: Medium | H92: 45147 | I92: 45152 | J92: Yes | K92: 45162
A93: =A92+1 -> 90 | B93: P2P | C93: AP1.10 | D93: Direct Payable attachment types | E93: Procurement | F93: Medium | H93: 45147 | I93: 45152 | J93: Yes | K93: 45162
A94: =A93+1 -> 91 | B94: P2P | C94: AP1.11 | D94: Fields for EFT to be captured on bank record | E94: Procurement | F94: High | H94: 45147 | I94: 45152 | J94: Yes | K94: 45166
A95: =A94+1 -> 92 | B95: P2P | C95: AP1.11 | D95: Invoice Payment Methods | E95: Procurement | F95: High | H95: 45147 | I95: 45152 | J95: Yes | K95: 45166
A96: =A95+1 -> 93 | B96: P2P | C96: AP1.12 | D96: Payments approval DOA (GL Disbursment) | E96: Procurement | F96: High | H96: 45147 | I96: 45152 | J96: Yes | K96: 45166
A97: =A96+1 -> 94 | B97: P2P | C97: AP1.13 | D97: Payment Attachment types | E97: Procurement | F97: Medium | H97: 45147 | I97: 45152 | J97: Yes | K97: 45166
A98: =A97+1 -> 95 | B98: P2P | C98: Additional Notes | D98: Process for cancelling PO | E98: Procurement | F98: Medium | H98: 45147 | I98: 45152 | J98: Yes | K98: 45166
A99: =A98+1 -> 96 | B99: P2P | C99: Additional Notes | D99: Terms and Conditions to printed on PO - Static Field | E99: Procurement | F99: High | H99: 45147 | I99: 45152 | J99: No
A100: =A99+1 -> 97 | B100: P2P | C100: AP3.1 | D100: Bank EFT Format | E100: Finance | F100: High | H100: 45147 | I100: 45152 | J100: Yes | K100: 45166
...
